[
    {
        "rank": 1,
        "players": [
            {
                "id": "562",
                "countryAbbreviation": "DEN",
                "countryFlagUrl": "https://www.badmintoncn.com/cbo_star/images/bwflag/denmark.png",
                "avatarUrl": "https://www.badmintoncn.com/cbo_star/upstar/562.jpg",
                "chineseName": "安赛龙",
                "englishName": "Viktor Axelsen"
            }
        ],
        "rankTrend": 0,
        "tournaments": 17,
        "points": 32020
    },
    {
        "rank": 2,
        "players": [
            {
                "id": "595",
                "countryAbbreviation": "JPN",
                "countryFlagUrl": "https://www.badmintoncn.com/cbo_star/images/bwflag/japan.png",
                "avatarUrl": "https://www.badmintoncn.com/cbo_star/upstar/595.jpg",
                "chineseName": "桃田贤斗",
                "englishName": "Kento Momota"
            }
        ],
        "rankTrend": 0,
        "tournaments": 12,
        "points": 27093
    },
    {
        "rank": 3,
        "players": [
            {
                "id": "664",
                "countryAbbreviation": "IND",
                "countryFlagUrl": "https://www.badmintoncn.com/cbo_star/images/bwflag/india.png",
                "avatarUrl": "https://www.badmintoncn.com/cbo_star/upstar/664.jpg",
                "chineseName": "萨米尔·维尔马",
                "englishName": "Sameer VERMA"
            }
        ],
        "rankTrend": 0,
        "tournaments": 11,
        "points": 26624
    },
    {
        "rank": 4,
        "players": [
            {
                "id": "1318",
                "countryAbbreviation": "THA",
                "countryFlagUrl": "https://www.badmintoncn.com/cbo_star/images/bwflag/thailand.png",
                "avatarUrl": "https://www.badmintoncn.com/cbo_star/upstar/1318_1750671010.jpg",
                "chineseName": "科希特·菲特普拉达",
                "englishName": "Khosit Phetpradab"
            }
        ],
        "rankTrend": 0,
        "tournaments": 12,
        "points": 24302
    },
    {
        "rank": 5,
        "players": [
            {
                "id": "977",
                "countryAbbreviation": "MAS",
                "countryFlagUrl": "https://www.badmintoncn.com/cbo_star/images/bwflag/malaysia.png",
                "avatarUrl": "https://www.badmintoncn.com/cbo_star/upstar/977.jpg",
                "chineseName": "宋俊伟",
                "englishName": "Soong Joo Ven"
            }
        ],
        "rankTrend": 0,
        "tournaments": 12,
        "points": 20100
    },
    {
        "rank": 6,
        "players": [
            {
                "id": "1121",
                "countryAbbreviation": "THA",
                "countryFlagUrl": "https://www.badmintoncn.com/cbo_star/images/bwflag/thailand.png",
                "avatarUrl": "https://www.badmintoncn.com/cbo_star/upstar/1121.jpg",
                "chineseName": "西蒂空·达玛新",
                "englishName": "Sitthikom THAMMASIN"
            }
        ],
        "rankTrend": 0,
        "tournaments": 13,
        "points": 19368
    },
    {
        "rank": 7,
        "players": [
            {
                "id": "675",
                "countryAbbreviation": "HKG",
                "countryFlagUrl": "https://www.badmintoncn.com/cbo_star/images/bwflag/hongkongchina.png",
                "avatarUrl": "https://www.badmintoncn.com/cbo_star/upstar/675.jpg",
                "chineseName": "伍家朗",
                "englishName": "Angus Ng Ka Long"
            }
        ],
        "rankTrend": 0,
        "tournaments": 9,
        "points": 18823
    },
    {
        "rank": 8,
        "players": [
            {
                "id": "699",
                "countryAbbreviation": "INA",
                "countryFlagUrl": "https://www.badmintoncn.com/cbo_star/images/bwflag/indonesia.png",
                "avatarUrl": "https://www.badmintoncn.com/cbo_star/upstar/699.jpg",
                "chineseName": "威斯奴·尤利·普拉塞特约",
                "englishName": "Wisnu Yuli Prasetyo"
            }
        ],
        "rankTrend": 1,
        "tournaments": 10,
        "points": 18682
    },
    {
        "rank": 9,
        "players": [
            {
                "id": "6086",
                "countryAbbreviation": "SVK",
                "countryFlagUrl": "https://www.badmintoncn.com/cbo_star/images/bwflag/slovakia.png",
                "avatarUrl": "https://www.badmintoncn.com/cbo_star/upstar/6086_1703229788.jpg",
                "chineseName": "马泰·赫利尼坎",
                "englishName": "Matej HLINICAN"
            }
        ],
        "rankTrend": -1,
        "tournaments": 11,
        "points": 17960
    },
    {
        "rank": 10,
        "players": [
            {
                "id": "1769",
                "countryAbbreviation": "FIN",
                "countryFlagUrl": "https://www.badmintoncn.com/cbo_star/images/bwflag/finland.png",
                "avatarUrl": "https://www.badmintoncn.com/cbo_star/upstar/1769.jpg",
                "chineseName": "卡尔·科尔约宁",
                "englishName": "Kalle KOLJONEN"
            }
        ],
        "rankTrend": 0,
        "tournaments": 12,
        "points": 16022
    },
    {
        "rank": 11,
        "players": [
            {
                "id": "4237",
                "countryAbbreviation": "AUT",
                "countryFlagUrl": "https://www.badmintoncn.com/cbo_star/images/bwflag/austria.png",
                "avatarUrl": "https://www.badmintoncn.com/cbo_star/upstar/4237.jpg",
                "chineseName": "马蒂亚·阿尔默",
                "englishName": "Matthias ALMER"
            }
        ],
        "rankTrend": 0,
        "tournaments": 10,
        "points": 14833
    },
    {
        "rank": 12,
        "players": [
            {
                "id": "1656",
                "countryAbbreviation": "INA",
                "countryFlagUrl": "https://www.badmintoncn.com/cbo_star/images/bwflag/indonesia.png",
                "avatarUrl": "https://www.badmintoncn.com/cbo_star/upstar/1656.jpg",
                "chineseName": "舍沙·海仁·雷斯塔维托",
                "englishName": "Shesar Hiren Rhustavito"
            }
        ],
        "rankTrend": 0,
        "tournaments": 9,
        "points": 14670
    },
    {
        "rank": 13,
        "players": [
            {
                "id": "6456",
                "countryAbbreviation": "IND",
                "countryFlagUrl": "https://www.badmintoncn.com/cbo_star/images/bwflag/india.png",
                "avatarUrl": "https://www.badmintoncn.com/cbo_star/upstar/6456_1701075700.jpg",
                "chineseName": "C. 罗希特·亚达夫",
                "englishName": "C. Rohit Yadav"
            }
        ],
        "rankTrend": 0,
        "tournaments": 7,
        "points": 13190
    },
    {
        "rank": 14,
        "players": [
            {
                "id": "2454",
                "countryAbbreviation": "IRL",
                "countryFlagUrl": "https://www.badmintoncn.com/cbo_star/images/bwflag/ireland.png",
                "avatarUrl": "https://www.badmintoncn.com/cbo_star/upstar/2454_1745826491.jpg",
                "chineseName": "乔纳森·多兰",
                "englishName": "Jonathan DOLAN"
            }
        ],
        "rankTrend": 0,
        "tournaments": 4,
        "points": 12920
    },
    {
        "rank": 15,
        "players": [
            {
                "id": "2211",
                "countryAbbreviation": "CZE",
                "countryFlagUrl": "https://www.badmintoncn.com/cbo_star/images/bwflag/czechrepublic.png",
                "avatarUrl": "https://www.badmintoncn.com/cbo_star/upstar/2211.jpg",
                "chineseName": "亚当·门德雷克",
                "englishName": "Adam MENDREK"
            }
        ],
        "rankTrend": 10,
        "tournaments": 8,
        "points": 12040
    },
    {
        "rank": 16,
        "players": [
            {
                "id": "7382",
                "countryAbbreviation": "INA",
                "countryFlagUrl": "https://www.badmintoncn.com/cbo_star/images/bwflag/indonesia.png",
                "avatarUrl": "https://www.badmintoncn.com/cbo_star/upstar/7382_1716173372.jpg",
                "chineseName": "马赫布布·托米·阿齐赞",
                "englishName": "Mahbub THOMI AZIZAN"
            }
        ],
        "rankTrend": -1,
        "tournaments": 7,
        "points": 11780
    },
    {
        "rank": 17,
        "players": [
            {
                "id": "1889",
                "countryAbbreviation": "FRA",
                "countryFlagUrl": "https://www.badmintoncn.com/cbo_star/images/bwflag/france.png",
                "avatarUrl": "https://www.badmintoncn.com/cbo_star/upstar/1889.jpg",
                "chineseName": "朱利安·马尤",
                "englishName": "Julien MAIO"
            }
        ],
        "rankTrend": -1,
        "tournaments": 10,
        "points": 11760
    },
    {
        "rank": 18,
        "players": [
            {
                "id": "1132",
                "countryAbbreviation": "MAS",
                "countryFlagUrl": "https://www.badmintoncn.com/cbo_star/images/bwflag/malaysia.png",
                "avatarUrl": "https://www.badmintoncn.com/cbo_star/upstar/1132_1744164675.jpg",
                "chineseName": "苏德智",
                "englishName": "Soo Teck Zhi"
            }
        ],
        "rankTrend": -1,
        "tournaments": 9,
        "points": 11360
    },
    {
        "rank": 19,
        "players": [
            {
                "id": "4024",
                "countryAbbreviation": "ESP",
                "countryFlagUrl": "https://www.badmintoncn.com/cbo_star/images/bwflag/spain.png",
                "avatarUrl": "https://www.badmintoncn.com/cbo_star/images/male.jpg",
                "chineseName": "维克多·马丁",
                "englishName": "Victor MARTIN"
            }
        ],
        "rankTrend": -1,
        "tournaments": 5,
        "points": 11098
    },
    {
        "rank": 20,
        "players": [
            {
                "id": "1136",
                "countryAbbreviation": "TPE",
                "countryFlagUrl": "https://www.badmintoncn.com/cbo_star/images/bwflag/chinesetaipei.png",
                "avatarUrl": "https://www.badmintoncn.com/cbo_star/upstar/1136.jpg",
                "chineseName": "王子维",
                "englishName": "Wang Tzu Wei"
            }
        ],
        "rankTrend": -1,
        "tournaments": 9,
        "points": 11013
    },
    {
        "rank": 21,
        "players": [
            {
                "id": "2484",
                "countryAbbreviation": "KOR",
                "countryFlagUrl": "https://www.badmintoncn.com/cbo_star/images/bwflag/korea.png",
                "avatarUrl": "https://www.badmintoncn.com/cbo_star/upstar/2484.jpg",
                "chineseName": "全奕陈",
                "englishName": "JEON Hyeok Jin"
            }
        ],
        "rankTrend": -1,
        "tournaments": 4,
        "points": 10620
    },
    {
        "rank": 22,
        "players": [
            {
                "id": "22076",
                "countryAbbreviation": "ESP",
                "countryFlagUrl": "https://www.badmintoncn.com/cbo_star/images/bwflag/spain.png",
                "avatarUrl": "https://www.badmintoncn.com/cbo_star/upstar/22076_1719368354.jpg",
                "chineseName": "艾托尔·阿雷扎",
                "englishName": "Aitor ARRAIZA"
            }
        ],
        "rankTrend": -1,
        "tournaments": 4,
        "points": 10520
    },
    {
        "rank": 23,
        "players": [
            {
                "id": "680",
                "countryAbbreviation": "KOR",
                "countryFlagUrl": "https://www.badmintoncn.com/cbo_star/images/bwflag/korea.png",
                "avatarUrl": "https://www.badmintoncn.com/cbo_star/upstar/680.jpg",
                "chineseName": "许侊熙",
                "englishName": "Heo Kwang Hee"
            }
        ],
        "rankTrend": -1,
        "tournaments": 5,
        "points": 10450
    },
    {
        "rank": 24,
        "players": [
            {
                "id": "3715",
                "countryAbbreviation": "FRA",
                "countryFlagUrl": "https://www.badmintoncn.com/cbo_star/images/bwflag/france.png",
                "avatarUrl": "https://www.badmintoncn.com/cbo_star/upstar/3715_1720516721.jpg",
                "chineseName": "乔斯林·德尚",
                "englishName": "Jocelyn DESCHAMP"
            }
        ],
        "rankTrend": -1,
        "tournaments": 8,
        "points": 10320
    },
    {
        "rank": 25,
        "players": [
            {
                "id": "1909",
                "countryAbbreviation": "CZE",
                "countryFlagUrl": "https://www.badmintoncn.com/cbo_star/images/bwflag/czechrepublic.png",
                "avatarUrl": "https://www.badmintoncn.com/cbo_star/upstar/1909.jpg",
                "chineseName": "贾罗米尔·贾纳切克",
                "englishName": "Jaromir JANACEK"
            }
        ],
        "rankTrend": 3,
        "tournaments": 11,
        "points": 10160
    },
    {
        "rank": 26,
        "players": [
            {
                "id": "13616",
                "countryAbbreviation": "SLO",
                "countryFlagUrl": "https://www.badmintoncn.com/cbo_star/images/bwflag/slovenia.png",
                "avatarUrl": "https://www.badmintoncn.com/cbo_star/upstar/13616_1711007184.jpg",
                "chineseName": "米贾·塞姆罗夫",
                "englishName": "Mitja SEMROV"
            }
        ],
        "rankTrend": 10,
        "tournaments": 10,
        "points": 10160
    },
    {
        "rank": 27,
        "players": [
            {
                "id": "4321",
                "countryAbbreviation": "INA",
                "countryFlagUrl": "https://www.badmintoncn.com/cbo_star/images/bwflag/indonesia.png",
                "avatarUrl": "https://www.badmintoncn.com/cbo_star/upstar/4321_1718268479.jpg",
                "chineseName": "阿里夫·拉马丹",
                "englishName": "Arif RAMADHAN"
            }
        ],
        "rankTrend": -1,
        "tournaments": 6,
        "points": 9860
    },
    {
        "rank": 28,
        "players": [
            {
                "id": "1236",
                "countryAbbreviation": "INA",
                "countryFlagUrl": "https://www.badmintoncn.com/cbo_star/images/bwflag/indonesia.png",
                "avatarUrl": "https://www.badmintoncn.com/cbo_star/upstar/1236_1747640952.jpg",
                "chineseName": "菲克里·伊赫桑迪·哈德马迪",
                "englishName": "Fikri Ihsandi Hadmadi"
            }
        ],
        "rankTrend": -1,
        "tournaments": 5,
        "points": 9840
    },
    {
        "rank": 29,
        "players": [
            {
                "id": "13805",
                "countryAbbreviation": "SGP",
                "countryFlagUrl": "https://www.badmintoncn.com/cbo_star/images/bwflag/singapore.png",
                "avatarUrl": "https://www.badmintoncn.com/cbo_star/upstar/13805_1721643061.jpg",
                "chineseName": "Soon Lee Gerald ONG",
                "englishName": "Soon Lee Gerald ONG"
            }
        ],
        "rankTrend": 0,
        "tournaments": 8,
        "points": 9378
    },
    {
        "rank": 30,
        "players": [
            {
                "id": "6544",
                "countryAbbreviation": "FRA",
                "countryFlagUrl": "https://www.badmintoncn.com/cbo_star/images/bwflag/france.png",
                "avatarUrl": "https://www.badmintoncn.com/cbo_star/upstar/6544.jpg",
                "chineseName": "皮耶里克·卡约特",
                "englishName": "Pierrick CAJOT"
            }
        ],
        "rankTrend": 0,
        "tournaments": 5,
        "points": 9320
    },
    {
        "rank": 31,
        "players": [
            {
                "id": "1598",
                "countryAbbreviation": "ENG",
                "countryFlagUrl": "https://www.badmintoncn.com/cbo_star/images/bwflag/england.png",
                "avatarUrl": "https://www.badmintoncn.com/cbo_star/upstar/1598.jpg",
                "chineseName": "汤姆·沃尔芬登",
                "englishName": "Tom Wolfenden"
            }
        ],
        "rankTrend": 1,
        "tournaments": 8,
        "points": 9110
    },
    {
        "rank": 32,
        "players": [
            {
                "id": "9323",
                "countryAbbreviation": "POR",
                "countryFlagUrl": "https://www.badmintoncn.com/cbo_star/images/bwflag/portugal.png",
                "avatarUrl": "https://www.badmintoncn.com/cbo_star/upstar/9323_1709631843.jpg",
                "chineseName": "布鲁诺·卡瓦略",
                "englishName": "Bruno CARVALHO"
            }
        ],
        "rankTrend": 1,
        "tournaments": 8,
        "points": 9080
    },
    {
        "rank": 33,
        "players": [
            {
                "id": "5388",
                "countryAbbreviation": "KOR",
                "countryFlagUrl": "https://www.badmintoncn.com/cbo_star/images/bwflag/korea.png",
                "avatarUrl": "https://www.badmintoncn.com/cbo_star/upstar/5388_1732848655.jpg",
                "chineseName": "金东柱",
                "englishName": "KIM Dong Ju"
            }
        ],
        "rankTrend": 1,
        "tournaments": 5,
        "points": 9080
    },
    {
        "rank": 34,
        "players": [
            {
                "id": "13432",
                "countryAbbreviation": "CRO",
                "countryFlagUrl": "https://www.badmintoncn.com/cbo_star/images/bwflag/croatia.png",
                "avatarUrl": "https://www.badmintoncn.com/cbo_star/upstar/13432_1752460128.jpg",
                "chineseName": "伊万·图卡科维奇",
                "englishName": "Ivan TUCAKOVIC"
            }
        ],
        "rankTrend": -10,
        "tournaments": 8,
        "points": 8960
    },
    {
        "rank": 35,
        "players": [
            {
                "id": "5691",
                "countryAbbreviation": "IND",
                "countryFlagUrl": "https://www.badmintoncn.com/cbo_star/images/bwflag/india.png",
                "avatarUrl": "https://www.badmintoncn.com/cbo_star/upstar/5691_1727319199.jpg",
                "chineseName": "普拉图尔·乔希",
                "englishName": "Pratul JOSHI"
            }
        ],
        "rankTrend": 0,
        "tournaments": 6,
        "points": 8925
    },
    {
        "rank": 36,
        "players": [
            {
                "id": "8078",
                "countryAbbreviation": "SCO",
                "countryFlagUrl": "https://www.badmintoncn.com/cbo_star/images/bwflag/scotland.png",
                "avatarUrl": "https://www.badmintoncn.com/cbo_star/upstar/8078_1755138261.jpg",
                "chineseName": "乔什·尼尔",
                "englishName": "Josh NEIL"
            }
        ],
        "rankTrend": 1,
        "tournaments": 5,
        "points": 8820
    },
    {
        "rank": 37,
        "players": [
            {
                "id": "7008",
                "countryAbbreviation": "MAS",
                "countryFlagUrl": "https://www.badmintoncn.com/cbo_star/images/bwflag/malaysia.png",
                "avatarUrl": "https://www.badmintoncn.com/cbo_star/upstar/7008_1708239002.jpg",
                "chineseName": "艾伟健",
                "englishName": "AI Wei Jian"
            }
        ],
        "rankTrend": 1,
        "tournaments": 7,
        "points": 8760
    },
    {
        "rank": 38,
        "players": [
            {
                "id": "1083",
                "countryAbbreviation": "THA",
                "countryFlagUrl": "https://www.badmintoncn.com/cbo_star/images/bwflag/thailand.png",
                "avatarUrl": "https://www.badmintoncn.com/cbo_star/upstar/1083_1744168218.jpg",
                "chineseName": "潘纳维",
                "englishName": "Pannawit Thongnuam"
            }
        ],
        "rankTrend": 1,
        "tournaments": 6,
        "points": 8680
    },
    {
        "rank": 39,
        "players": [
            {
                "id": "978",
                "countryAbbreviation": "INA",
                "countryFlagUrl": "https://www.badmintoncn.com/cbo_star/images/bwflag/indonesia.png",
                "avatarUrl": "https://www.badmintoncn.com/cbo_star/upstar/978.jpg",
                "chineseName": "苏德拉查",
                "englishName": "Sudrajat Panji Akbar"
            }
        ],
        "rankTrend": 1,
        "tournaments": 5,
        "points": 8510
    },
    {
        "rank": 40,
        "players": [
            {
                "id": "2406",
                "countryAbbreviation": "KOR",
                "countryFlagUrl": "https://www.badmintoncn.com/cbo_star/images/bwflag/korea.png",
                "avatarUrl": "https://www.badmintoncn.com/cbo_star/upstar/2406_1708396539.jpg",
                "chineseName": "郑在旭",
                "englishName": "JUNG Jae Wook"
            }
        ],
        "rankTrend": 1,
        "tournaments": 4,
        "points": 8420
    },
    {
        "rank": 41,
        "players": [
            {
                "id": "8068",
                "countryAbbreviation": "ENG",
                "countryFlagUrl": "https://www.badmintoncn.com/cbo_star/images/bwflag/england.png",
                "avatarUrl": "https://www.badmintoncn.com/cbo_star/upstar/8068_1745290216.jpg",
                "chineseName": "达伦·亚当森",
                "englishName": "Darren ADAMSON"
            }
        ],
        "rankTrend": 1,
        "tournaments": 6,
        "points": 8400
    },
    {
        "rank": 42,
        "players": [
            {
                "id": "9106",
                "countryAbbreviation": "TUR",
                "countryFlagUrl": "https://www.badmintoncn.com/cbo_star/images/bwflag/turkey.png",
                "avatarUrl": "https://www.badmintoncn.com/cbo_star/upstar/9106_1725417907.jpg",
                "chineseName": "埃尼斯·塞萨兰",
                "englishName": "Enis SESALAN"
            }
        ],
        "rankTrend": 10,
        "tournaments": 7,
        "points": 8360
    },
    {
        "rank": 43,
        "players": [
            {
                "id": "8801",
                "countryAbbreviation": "TUR",
                "countryFlagUrl": "https://www.badmintoncn.com/cbo_star/images/bwflag/turkey.png",
                "avatarUrl": "https://www.badmintoncn.com/cbo_star/upstar/8801_1703643326.jpg",
                "chineseName": "斯南·佐鲁",
                "englishName": "Sİnan ZORLU"
            }
        ],
        "rankTrend": 1,
        "tournaments": 8,
        "points": 8250
    },
    {
        "rank": 44,
        "players": [
            {
                "id": "1731",
                "countryAbbreviation": "JPN",
                "countryFlagUrl": "https://www.badmintoncn.com/cbo_star/images/bwflag/japan.png",
                "avatarUrl": "https://www.badmintoncn.com/cbo_star/upstar/1731.jpg",
                "chineseName": "古贺辉",
                "englishName": "Akira KOGA"
            }
        ],
        "rankTrend": 1,
        "tournaments": 4,
        "points": 7970
    },
    {
        "rank": 45,
        "players": [
            {
                "id": "8020",
                "countryAbbreviation": "CAN",
                "countryFlagUrl": "https://www.badmintoncn.com/cbo_star/images/bwflag/canada.png",
                "avatarUrl": "https://www.badmintoncn.com/cbo_star/upstar/8020_1702524511.jpg",
                "chineseName": "安德鲁·德索萨",
                "englishName": "Andrew D'SOUZA"
            }
        ],
        "rankTrend": 2,
        "tournaments": 7,
        "points": 7930
    },
    {
        "rank": 46,
        "players": [
            {
                "id": "1423",
                "countryAbbreviation": "INA",
                "countryFlagUrl": "https://www.badmintoncn.com/cbo_star/images/bwflag/indonesia.png",
                "avatarUrl": "https://www.badmintoncn.com/cbo_star/upstar/1423_1753350405.jpg",
                "chineseName": "雷西·奥里扎",
                "englishName": "Reksy Aureza Megananda"
            }
        ],
        "rankTrend": 2,
        "tournaments": 5,
        "points": 7910
    },
    {
        "rank": 47,
        "players": [
            {
                "id": "3664",
                "countryAbbreviation": "FIN",
                "countryFlagUrl": "https://www.badmintoncn.com/cbo_star/images/bwflag/finland.png",
                "avatarUrl": "https://www.badmintoncn.com/cbo_star/upstar/3664_1751621639.jpg",
                "chineseName": "伊卡·海诺",
                "englishName": "Iikka HEINO"
            }
        ],
        "rankTrend": 2,
        "tournaments": 7,
        "points": 7840
    },
    {
        "rank": 48,
        "players": [
            {
                "id": "2990",
                "countryAbbreviation": "INA",
                "countryFlagUrl": "https://www.badmintoncn.com/cbo_star/images/bwflag/indonesia.png",
                "avatarUrl": "https://www.badmintoncn.com/cbo_star/upstar/2990_1704703169.jpg",
                "chineseName": "亨利科·霍·维博沃",
                "englishName": "Henrikho KHO WIBOWO"
            }
        ],
        "rankTrend": -5,
        "tournaments": 7,
        "points": 7800
    },
    {
        "rank": 49,
        "players": [
            {
                "id": "12812",
                "countryAbbreviation": "DEN",
                "countryFlagUrl": "https://www.badmintoncn.com/cbo_star/images/bwflag/denmark.png",
                "avatarUrl": "https://www.badmintoncn.com/cbo_star/upstar/12812_1715331828.jpg",
                "chineseName": "拉斯马斯·格里尔",
                "englishName": "Rasmus Grill NOES"
            }
        ],
        "rankTrend": 1,
        "tournaments": 8,
        "points": 7773
    },
    {
        "rank": 50,
        "players": [
            {
                "id": "13648",
                "countryAbbreviation": "RUS",
                "countryFlagUrl": "https://www.badmintoncn.com/cbo_star/images/bwflag/russia.png",
                "avatarUrl": "https://www.badmintoncn.com/cbo_star/upstar/13648_1745303756.jpg",
                "chineseName": "基里尔·博亚尔斯基",
                "englishName": "Kirill BOYARSKIY"
            }
        ],
        "rankTrend": 1,
        "tournaments": 5,
        "points": 7720
    },
    {
        "rank": 51,
        "players": [
            {
                "id": "1929",
                "countryAbbreviation": "IRL",
                "countryFlagUrl": "https://www.badmintoncn.com/cbo_star/images/bwflag/ireland.png",
                "avatarUrl": "https://www.badmintoncn.com/cbo_star/upstar/1929.jpg",
                "chineseName": "约书亚·马吉",
                "englishName": "Joshua MAGEE"
            }
        ],
        "rankTrend": 2,
        "tournaments": 5,
        "points": 7430
    },
    {
        "rank": 52,
        "players": [
            {
                "id": "1918",
                "countryAbbreviation": "AUT",
                "countryFlagUrl": "https://www.badmintoncn.com/cbo_star/images/bwflag/austria.png",
                "avatarUrl": "https://www.badmintoncn.com/cbo_star/upstar/1918.jpg",
                "chineseName": "多米尼克·斯蒂普斯",
                "englishName": "Dominik STIPSITS"
            }
        ],
        "rankTrend": 2,
        "tournaments": 8,
        "points": 7340
    },
    {
        "rank": 53,
        "players": [
            {
                "id": "7776",
                "countryAbbreviation": "BEL",
                "countryFlagUrl": "https://www.badmintoncn.com/cbo_star/images/bwflag/belgium.png",
                "avatarUrl": "https://www.badmintoncn.com/cbo_star/upstar/7776_1710321231.jpg",
                "chineseName": "马里恩·普特",
                "englishName": "Marijn PUT"
            }
        ],
        "rankTrend": 2,
        "tournaments": 9,
        "points": 7330
    },
    {
        "rank": 54,
        "players": [
            {
                "id": "1761",
                "countryAbbreviation": "RUS",
                "countryFlagUrl": "https://www.badmintoncn.com/cbo_star/images/bwflag/russia.png",
                "avatarUrl": "https://www.badmintoncn.com/cbo_star/upstar/1761.jpg",
                "chineseName": "谢尔盖·西兰特",
                "englishName": "Sergey SIRANT"
            }
        ],
        "rankTrend": 2,
        "tournaments": 6,
        "points": 7328
    },
    {
        "rank": 55,
        "players": [
            {
                "id": "13310",
                "countryAbbreviation": "SVK",
                "countryFlagUrl": "https://www.badmintoncn.com/cbo_star/images/bwflag/slovakia.png",
                "avatarUrl": "https://www.badmintoncn.com/cbo_star/images/male.jpg",
                "chineseName": "David BALUCHA",
                "englishName": "David BALUCHA"
            }
        ],
        "rankTrend": 2,
        "tournaments": 9,
        "points": 7160
    },
    {
        "rank": 56,
        "players": [
            {
                "id": "6043",
                "countryAbbreviation": "POL",
                "countryFlagUrl": "https://www.badmintoncn.com/cbo_star/images/bwflag/poland.png",
                "avatarUrl": "https://www.badmintoncn.com/cbo_star/upstar/6043_1705372828.jpg",
                "chineseName": "克日什托夫·雅科丘克",
                "englishName": "Krzysztof JAKOWCZUK"
            }
        ],
        "rankTrend": -10,
        "tournaments": 3,
        "points": 7040
    },
    {
        "rank": 57,
        "players": [
            {
                "id": "3550",
                "countryAbbreviation": "IND",
                "countryFlagUrl": "https://www.badmintoncn.com/cbo_star/images/bwflag/india.png",
                "avatarUrl": "https://www.badmintoncn.com/cbo_star/upstar/3550.jpg",
                "chineseName": "哈希尔·丹尼",
                "englishName": "Harsheel DANI"
            }
        ],
        "rankTrend": 2,
        "tournaments": 2,
        "points": 7000
    },
    {
        "rank": 58,
        "players": [
            {
                "id": "1181",
                "countryAbbreviation": "INA",
                "countryFlagUrl": "https://www.badmintoncn.com/cbo_star/images/bwflag/indonesia.png",
                "avatarUrl": "https://www.badmintoncn.com/cbo_star/upstar/1181.jpg",
                "chineseName": "伊赫桑·毛拉纳·穆斯托法",
                "englishName": "Ihsan Maulana Mustofa"
            }
        ],
        "rankTrend": 2,
        "tournaments": 4,
        "points": 6950
    },
    {
        "rank": 59,
        "players": [
            {
                "id": "8049",
                "countryAbbreviation": "NED",
                "countryFlagUrl": "https://www.badmintoncn.com/cbo_star/images/bwflag/netherlands.png",
                "avatarUrl": "https://www.badmintoncn.com/cbo_star/upstar/8049_1713323784.jpg",
                "chineseName": "贾斯汀·蒂文",
                "englishName": "Justin TEEUWEN"
            }
        ],
        "rankTrend": 2,
        "tournaments": 5,
        "points": 6720
    },
    {
        "rank": 60,
        "players": [
            {
                "id": "2506",
                "countryAbbreviation": "GER",
                "countryFlagUrl": "https://www.badmintoncn.com/cbo_star/images/bwflag/germany.png",
                "avatarUrl": "https://www.badmintoncn.com/cbo_star/upstar/2506.jpg",
                "chineseName": "拉尔斯·舍恩斯勒",
                "englishName": "Lars SCHAENZLER"
            }
        ],
        "rankTrend": 2,
        "tournaments": 4,
        "points": 6690
    },
    {
        "rank": 61,
        "players": [
            {
                "id": "2229",
                "countryAbbreviation": "ENG",
                "countryFlagUrl": "https://www.badmintoncn.com/cbo_star/images/bwflag/england.png",
                "avatarUrl": "https://www.badmintoncn.com/cbo_star/upstar/2229.jpg",
                "chineseName": "亚历克斯·莱恩",
                "englishName": "Alex LANE"
            }
        ],
        "rankTrend": 2,
        "tournaments": 4,
        "points": 6600
    },
    {
        "rank": 62,
        "players": [
            {
                "id": "8342",
                "countryAbbreviation": "SLO",
                "countryFlagUrl": "https://www.badmintoncn.com/cbo_star/images/bwflag/slovenia.png",
                "avatarUrl": "https://www.badmintoncn.com/cbo_star/upstar/8342_1745219052.jpg",
                "chineseName": "赞·拉兹尼克",
                "englishName": "Žan LAZNIK"
            }
        ],
        "rankTrend": 12,
        "tournaments": 6,
        "points": 6480
    },
    {
        "rank": 63,
        "players": [
            {
                "id": "1223",
                "countryAbbreviation": "CHN",
                "countryFlagUrl": "https://www.badmintoncn.com/cbo_star/images/bwflag/china.png",
                "avatarUrl": "https://www.badmintoncn.com/cbo_star/upstar/1223_1755229195.jpg",
                "chineseName": "郭凯",
                "englishName": "Guo Kai"
            }
        ],
        "rankTrend": 2,
        "tournaments": 2,
        "points": 6320
    },
    {
        "rank": 64,
        "players": [
            {
                "id": "7452",
                "countryAbbreviation": "ENG",
                "countryFlagUrl": "https://www.badmintoncn.com/cbo_star/images/bwflag/england.png",
                "avatarUrl": "https://www.badmintoncn.com/cbo_star/upstar/7452_1711940971.jpg",
                "chineseName": "里斯·沃克",
                "englishName": "Rhys WALKER"
            }
        ],
        "rankTrend": 2,
        "tournaments": 14,
        "points": 6309
    },
    {
        "rank": 65,
        "players": [
            {
                "id": "13249",
                "countryAbbreviation": "FRA",
                "countryFlagUrl": "https://www.badmintoncn.com/cbo_star/images/bwflag/france.png",
                "avatarUrl": "https://www.badmintoncn.com/cbo_star/upstar/13249_1720600832.jpg",
                "chineseName": "安托万·洛迪奥特",
                "englishName": "Antoine LODIOT"
            }
        ],
        "rankTrend": 2,
        "tournaments": 9,
        "points": 6290
    },
    {
        "rank": 66,
        "players": [
            {
                "id": "3686",
                "countryAbbreviation": "SUI",
                "countryFlagUrl": "https://www.badmintoncn.com/cbo_star/images/bwflag/switzerland.png",
                "avatarUrl": "https://www.badmintoncn.com/cbo_star/upstar/3686_1698632849.jpg",
                "chineseName": "马赛厄斯·邦尼",
                "englishName": "Mathias BONNY"
            }
        ],
        "rankTrend": 2,
        "tournaments": 5,
        "points": 6280
    },
    {
        "rank": 67,
        "players": [
            {
                "id": "8356",
                "countryAbbreviation": "RUS",
                "countryFlagUrl": "https://www.badmintoncn.com/cbo_star/images/bwflag/russia.png",
                "avatarUrl": "https://www.badmintoncn.com/cbo_star/upstar/8356_1735541613.jpg",
                "chineseName": "弗拉迪斯拉夫·索洛维耶夫",
                "englishName": "Vladislav SOLOVIEV"
            }
        ],
        "rankTrend": 31,
        "tournaments": 4,
        "points": 6200
    },
    {
        "rank": 68,
        "players": [
            {
                "id": "5795",
                "countryAbbreviation": "FIN",
                "countryFlagUrl": "https://www.badmintoncn.com/cbo_star/images/bwflag/finland.png",
                "avatarUrl": "https://www.badmintoncn.com/cbo_star/upstar/5795_1702448166.jpg",
                "chineseName": "乔纳斯·科霍宁",
                "englishName": "Joonas KORHONEN"
            }
        ],
        "rankTrend": 1,
        "tournaments": 6,
        "points": 6170
    },
    {
        "rank": 69,
        "players": [
            {
                "id": "1798",
                "countryAbbreviation": "RUS",
                "countryFlagUrl": "https://www.badmintoncn.com/cbo_star/images/bwflag/russia.png",
                "avatarUrl": "https://www.badmintoncn.com/cbo_star/upstar/1798.jpg",
                "chineseName": "罗季翁·阿利莫夫",
                "englishName": "Rodion ALIMOV"
            }
        ],
        "rankTrend": 58,
        "tournaments": 4,
        "points": 6160
    },
    {
        "rank": 70,
        "players": [
            {
                "id": "7637",
                "countryAbbreviation": "INA",
                "countryFlagUrl": "https://www.badmintoncn.com/cbo_star/images/bwflag/indonesia.png",
                "avatarUrl": "https://www.badmintoncn.com/cbo_star/upstar/7637_1741849030.jpg",
                "chineseName": "贾努阿里·阿里",
                "englishName": "Januari ARI"
            }
        ],
        "rankTrend": 0,
        "tournaments": 4,
        "points": 6100
    },
    {
        "rank": 71,
        "players": [
            {
                "id": "3949",
                "countryAbbreviation": "MAS",
                "countryFlagUrl": "https://www.badmintoncn.com/cbo_star/images/bwflag/malaysia.png",
                "avatarUrl": "https://www.badmintoncn.com/cbo_star/upstar/3949_1700547045.jpg",
                "chineseName": "张育汉",
                "englishName": "CHONG Yee Han"
            }
        ],
        "rankTrend": 0,
        "tournaments": 8,
        "points": 6020
    },
    {
        "rank": 72,
        "players": [
            {
                "id": "11581",
                "countryAbbreviation": "DEN",
                "countryFlagUrl": "https://www.badmintoncn.com/cbo_star/images/bwflag/denmark.png",
                "avatarUrl": "https://www.badmintoncn.com/cbo_star/upstar/11581_1740367149.jpg",
                "chineseName": "乔舒亚·埃佩",
                "englishName": "Joshua EIPE"
            }
        ],
        "rankTrend": 0,
        "tournaments": 3,
        "points": 5940
    },
    {
        "rank": 73,
        "players": [
            {
                "id": "2036",
                "countryAbbreviation": "HUN",
                "countryFlagUrl": "https://www.badmintoncn.com/cbo_star/images/bwflag/hungary.png",
                "avatarUrl": "https://www.badmintoncn.com/cbo_star/upstar/2036.jpg",
                "chineseName": "格格利·克劳斯",
                "englishName": "Gergely KRAUSZ"
            }
        ],
        "rankTrend": -42,
        "tournaments": 10,
        "points": 5900
    },
    {
        "rank": 74,
        "players": [
            {
                "id": "8834",
                "countryAbbreviation": "MEX",
                "countryFlagUrl": "https://www.badmintoncn.com/cbo_star/images/bwflag/mexico.png",
                "avatarUrl": "https://www.badmintoncn.com/cbo_star/upstar/8834_1721962801.jpg",
                "chineseName": "安德烈斯·夸里",
                "englishName": "Andres QUADRI"
            }
        ],
        "rankTrend": -1,
        "tournaments": 7,
        "points": 5890
    },
    {
        "rank": 75,
        "players": [
            {
                "id": "2524",
                "countryAbbreviation": "CRO",
                "countryFlagUrl": "https://www.badmintoncn.com/cbo_star/images/bwflag/croatia.png",
                "avatarUrl": "https://www.badmintoncn.com/cbo_star/upstar/2524.jpg",
                "chineseName": "菲利普·斯波尔贾雷克",
                "englishName": "Filip SPOLJAREC"
            }
        ],
        "rankTrend": -11,
        "tournaments": 11,
        "points": 5840
    },
    {
        "rank": 76,
        "players": [
            {
                "id": "10875",
                "countryAbbreviation": "EGY",
                "countryFlagUrl": "https://www.badmintoncn.com/cbo_star/images/bwflag/egypt.png",
                "avatarUrl": "https://www.badmintoncn.com/cbo_star/images/male.jpg",
                "chineseName": "Ahmed ABDELKADER",
                "englishName": "Ahmed ABDELKADER"
            }
        ],
        "rankTrend": -1,
        "tournaments": 6,
        "points": 5800
    },
    {
        "rank": 77,
        "players": [
            {
                "id": "6259",
                "countryAbbreviation": "SCO",
                "countryFlagUrl": "https://www.badmintoncn.com/cbo_star/images/bwflag/scotland.png",
                "avatarUrl": "https://www.badmintoncn.com/cbo_star/upstar/6259_1755510091.jpg",
                "chineseName": "本·托伦斯",
                "englishName": "Ben TORRANCE"
            }
        ],
        "rankTrend": -1,
        "tournaments": 7,
        "points": 5790
    },
    {
        "rank": 78,
        "players": [
            {
                "id": "649",
                "countryAbbreviation": "KOR",
                "countryFlagUrl": "https://www.badmintoncn.com/cbo_star/images/bwflag/korea.png",
                "avatarUrl": "https://www.badmintoncn.com/cbo_star/upstar/649.jpg",
                "chineseName": "崔率圭",
                "englishName": "Choi Sol Gyu"
            }
        ],
        "rankTrend": -1,
        "tournaments": 2,
        "points": 5670
    },
    {
        "rank": 79,
        "players": [
            {
                "id": "13907",
                "countryAbbreviation": "SRI",
                "countryFlagUrl": "https://www.badmintoncn.com/cbo_star/images/bwflag/srilanka.png",
                "avatarUrl": "https://www.badmintoncn.com/cbo_star/upstar/13907_1721184547.jpg",
                "chineseName": "帕莫达·考什卡·赫蒂亚拉奇",
                "englishName": "Pamodha Kaushika HETTIARACHCHI"
            }
        ],
        "rankTrend": -1,
        "tournaments": 5,
        "points": 5630
    },
    {
        "rank": 80,
        "players": [
            {
                "id": "12585",
                "countryAbbreviation": "UKR",
                "countryFlagUrl": "https://www.badmintoncn.com/cbo_star/images/bwflag/ukraine.png",
                "avatarUrl": "https://www.badmintoncn.com/cbo_star/upstar/12585_1717148906.jpg",
                "chineseName": "齐努霍夫·安德里",
                "englishName": "ZINUKHOV Andriy"
            }
        ],
        "rankTrend": -22,
        "tournaments": 5,
        "points": 5550
    },
    {
        "rank": 81,
        "players": [
            {
                "id": "13420",
                "countryAbbreviation": "UKR",
                "countryFlagUrl": "https://www.badmintoncn.com/cbo_star/images/bwflag/ukraine.png",
                "avatarUrl": "https://www.badmintoncn.com/cbo_star/images/male.jpg",
                "chineseName": "Andriy LACHKOV",
                "englishName": "Andriy LACHKOV"
            }
        ],
        "rankTrend": 1,
        "tournaments": 5,
        "points": 5430
    },
    {
        "rank": 82,
        "players": [
            {
                "id": "1573",
                "countryAbbreviation": "GER",
                "countryFlagUrl": "https://www.badmintoncn.com/cbo_star/images/bwflag/germany.png",
                "avatarUrl": "https://www.badmintoncn.com/cbo_star/upstar/1573_1720423117.jpg",
                "chineseName": "法比安·罗斯",
                "englishName": "Fabian ROTH"
            }
        ],
        "rankTrend": 1,
        "tournaments": 4,
        "points": 5410
    },
    {
        "rank": 83,
        "players": [
            {
                "id": "7030",
                "countryAbbreviation": "ENG",
                "countryFlagUrl": "https://www.badmintoncn.com/cbo_star/images/bwflag/england.png",
                "avatarUrl": "https://www.badmintoncn.com/cbo_star/upstar/7030_1713169720.jpg",
                "chineseName": "奥利弗·巴查拉",
                "englishName": "Oliver BACZALA"
            }
        ],
        "rankTrend": 1,
        "tournaments": 5,
        "points": 5360
    },
    {
        "rank": 84,
        "players": [
            {
                "id": "2228",
                "countryAbbreviation": "VIE",
                "countryFlagUrl": "https://www.badmintoncn.com/cbo_star/images/bwflag/vietnam.png",
                "avatarUrl": "https://www.badmintoncn.com/cbo_star/upstar/2228_1699951333.jpg",
                "chineseName": "范高强",
                "englishName": "Cao Cuong PHAM"
            }
        ],
        "rankTrend": 1,
        "tournaments": 6,
        "points": 5300
    },
    {
        "rank": 85,
        "players": [
            {
                "id": "7039",
                "countryAbbreviation": "IND",
                "countryFlagUrl": "https://www.badmintoncn.com/cbo_star/images/bwflag/india.png",
                "avatarUrl": "https://www.badmintoncn.com/cbo_star/upstar/7039_1735201525.jpg",
                "chineseName": "阿尔萨兰·纳克维",
                "englishName": "Arsalan NAQVI"
            }
        ],
        "rankTrend": 1,
        "tournaments": 5,
        "points": 5260
    },
    {
        "rank": 86,
        "players": [
            {
                "id": "12538",
                "countryAbbreviation": "IRL",
                "countryFlagUrl": "https://www.badmintoncn.com/cbo_star/images/bwflag/ireland.png",
                "avatarUrl": "https://www.badmintoncn.com/cbo_star/upstar/12538_1745561315.jpg",
                "chineseName": "利亚姆·奥利里",
                "englishName": "Liam O’ LEARY"
            }
        ],
        "rankTrend": 1,
        "tournaments": 5,
        "points": 5170
    },
    {
        "rank": 87,
        "players": [
            {
                "id": "1328",
                "countryAbbreviation": "IND",
                "countryFlagUrl": "https://www.badmintoncn.com/cbo_star/images/bwflag/india.png",
                "avatarUrl": "https://www.badmintoncn.com/cbo_star/upstar/1328_1755510046.jpg",
                "chineseName": "阿迪蒂亚·乔希",
                "englishName": "Aditya JOSHI"
            }
        ],
        "rankTrend": 1,
        "tournaments": 4,
        "points": 5130
    },
    {
        "rank": 88,
        "players": [
            {
                "id": "1359",
                "countryAbbreviation": "MAS",
                "countryFlagUrl": "https://www.badmintoncn.com/cbo_star/images/bwflag/malaysia.png",
                "avatarUrl": "https://www.badmintoncn.com/cbo_star/upstar/1359.jpg",
                "chineseName": "詹俊为",
                "englishName": "Cheam June Wei"
            }
        ],
        "rankTrend": 1,
        "tournaments": 7,
        "points": 5060
    },
    {
        "rank": 89,
        "players": [
            {
                "id": "7902",
                "countryAbbreviation": "POR",
                "countryFlagUrl": "https://www.badmintoncn.com/cbo_star/images/bwflag/portugal.png",
                "avatarUrl": "https://www.badmintoncn.com/cbo_star/upstar/7902_1703570547.jpg",
                "chineseName": "里卡多·西尔瓦",
                "englishName": "Ricardo SILVA"
            }
        ],
        "rankTrend": 1,
        "tournaments": 4,
        "points": 5000
    },
    {
        "rank": 90,
        "players": [
            {
                "id": "8336",
                "countryAbbreviation": "BUL",
                "countryFlagUrl": "https://www.badmintoncn.com/cbo_star/images/bwflag/bulgaria.png",
                "avatarUrl": "https://www.badmintoncn.com/cbo_star/upstar/8336_1710402749.jpg",
                "chineseName": "弗拉基米尔·希什科夫",
                "englishName": "Vladimir SHISHKOV"
            }
        ],
        "rankTrend": 7,
        "tournaments": 7,
        "points": 4990
    },
    {
        "rank": 91,
        "players": [
            {
                "id": "8570",
                "countryAbbreviation": "DEN",
                "countryFlagUrl": "https://www.badmintoncn.com/cbo_star/images/bwflag/denmark.png",
                "avatarUrl": "https://www.badmintoncn.com/cbo_star/upstar/8570_1730433071.jpg",
                "chineseName": "马蒂亚斯·蒙德比约",
                "englishName": "Mathias MUNDBJERG"
            }
        ],
        "rankTrend": 0,
        "tournaments": 7,
        "points": 4960
    },
    {
        "rank": 92,
        "players": [
            {
                "id": "1784",
                "countryAbbreviation": "ENG",
                "countryFlagUrl": "https://www.badmintoncn.com/cbo_star/images/bwflag/england.png",
                "avatarUrl": "https://www.badmintoncn.com/cbo_star/upstar/1784.jpg",
                "chineseName": "肖恩·文迪",
                "englishName": "Sean VENDY"
            }
        ],
        "rankTrend": 0,
        "tournaments": 4,
        "points": 4960
    },
    {
        "rank": 93,
        "players": [
            {
                "id": "2153",
                "countryAbbreviation": "IND",
                "countryFlagUrl": "https://www.badmintoncn.com/cbo_star/images/bwflag/india.png",
                "avatarUrl": "https://www.badmintoncn.com/cbo_star/upstar/2153.jpg",
                "chineseName": "考沙尔·达摩尔",
                "englishName": "Kaushal DHARMAMER"
            }
        ],
        "rankTrend": 0,
        "tournaments": 1,
        "points": 4900
    },
    {
        "rank": 94,
        "players": [
            {
                "id": "6897",
                "countryAbbreviation": "RUS",
                "countryFlagUrl": "https://www.badmintoncn.com/cbo_star/images/bwflag/russia.png",
                "avatarUrl": "https://www.badmintoncn.com/cbo_star/images/male.jpg",
                "chineseName": "亚历山大·布托维茨基",
                "englishName": "Alexander BUTOVETSTKIY"
            }
        ],
        "rankTrend": 0,
        "tournaments": 6,
        "points": 4890
    },
    {
        "rank": 95,
        "players": [
            {
                "id": "13790",
                "countryAbbreviation": "SVK",
                "countryFlagUrl": "https://www.badmintoncn.com/cbo_star/images/bwflag/slovakia.png",
                "avatarUrl": "https://www.badmintoncn.com/cbo_star/images/male.jpg",
                "chineseName": "Tadeas ZDARSKY",
                "englishName": "Tadeas ZDARSKY"
            }
        ],
        "rankTrend": 0,
        "tournaments": 7,
        "points": 4800
    },
    {
        "rank": 96,
        "players": [
            {
                "id": "7274",
                "countryAbbreviation": "MAS",
                "countryFlagUrl": "https://www.badmintoncn.com/cbo_star/images/bwflag/malaysia.png",
                "avatarUrl": "https://www.badmintoncn.com/cbo_star/upstar/7274_1703211507.jpg",
                "chineseName": "陈德翰",
                "englishName": "Teck Han TAN"
            }
        ],
        "rankTrend": 0,
        "tournaments": 3,
        "points": 4790
    },
    {
        "rank": 97,
        "players": [
            {
                "id": "13064",
                "countryAbbreviation": "POL",
                "countryFlagUrl": "https://www.badmintoncn.com/cbo_star/images/bwflag/poland.png",
                "avatarUrl": "https://www.badmintoncn.com/cbo_star/images/male.jpg",
                "chineseName": "马切伊·达布罗夫斯基",
                "englishName": "Maciej DABROWSKI"
            }
        ],
        "rankTrend": -18,
        "tournaments": 3,
        "points": 4680
    },
    {
        "rank": 98,
        "players": [
            {
                "id": "1495",
                "countryAbbreviation": "ENG",
                "countryFlagUrl": "https://www.badmintoncn.com/cbo_star/images/bwflag/england.png",
                "avatarUrl": "https://www.badmintoncn.com/cbo_star/upstar/1495_1745737050.jpg",
                "chineseName": "山姆·帕森斯",
                "englishName": "Sam Parsons"
            }
        ],
        "rankTrend": 1,
        "tournaments": 4,
        "points": 4670
    },
    {
        "rank": 99,
        "players": [
            {
                "id": "9105",
                "countryAbbreviation": "RUS",
                "countryFlagUrl": "https://www.badmintoncn.com/cbo_star/images/bwflag/russia.png",
                "avatarUrl": "https://www.badmintoncn.com/cbo_star/upstar/9105_1725848135.jpg",
                "chineseName": "安德烈·多洛托夫",
                "englishName": "Andrey DOLOTOV"
            }
        ],
        "rankTrend": -19,
        "tournaments": 4,
        "points": 4660
    },
    {
        "rank": 100,
        "players": [
            {
                "id": "11134",
                "countryAbbreviation": "POL",
                "countryFlagUrl": "https://www.badmintoncn.com/cbo_star/images/bwflag/poland.png",
                "avatarUrl": "https://www.badmintoncn.com/cbo_star/upstar/11134_1716798189.jpg",
                "chineseName": "皮奥特·瓦西卢克",
                "englishName": "Piotr WASILUK"
            }
        ],
        "rankTrend": 1,
        "tournaments": 3,
        "points": 4640
    }
]