[
    {
        "rank": 1,
        "players": [
            {
                "id": "1527",
                "countryAbbreviation": "THA",
                "countryFlagUrl": "https://www.badmintoncn.com/cbo_star/images/bwflag/thailand.png",
                "avatarUrl": "https://www.badmintoncn.com/cbo_star/upstar/1527_1713250301.jpg",
                "chineseName": "纳塔帕·特林卡吉",
                "englishName": "Natthapat Trinkajee"
            }
        ],
        "rankTrend": 5,
        "tournaments": 15,
        "points": 16825
    },
    {
        "rank": 2,
        "players": [
            {
                "id": "1477",
                "countryAbbreviation": "INA",
                "countryFlagUrl": "https://www.badmintoncn.com/cbo_star/images/bwflag/indonesia.png",
                "avatarUrl": "https://www.badmintoncn.com/cbo_star/upstar/1477.jpg",
                "chineseName": "里诺夫·里瓦尔迪",
                "englishName": "Rinov RIVALDY"
            }
        ],
        "rankTrend": 8,
        "tournaments": 8,
        "points": 13587
    },
    {
        "rank": 3,
        "players": [
            {
                "id": "1626",
                "countryAbbreviation": "IND",
                "countryFlagUrl": "https://www.badmintoncn.com/cbo_star/images/bwflag/india.png",
                "avatarUrl": "https://www.badmintoncn.com/cbo_star/upstar/1626.jpg",
                "chineseName": "萨维克赛拉吉·兰基雷迪",
                "englishName": "Satwiksairaj RANKIREDDY"
            }
        ],
        "rankTrend": 10,
        "tournaments": 10,
        "points": 12902
    },
    {
        "rank": 4,
        "players": [
            {
                "id": "2015",
                "countryAbbreviation": "IND",
                "countryFlagUrl": "https://www.badmintoncn.com/cbo_star/images/bwflag/india.png",
                "avatarUrl": "https://www.badmintoncn.com/cbo_star/upstar/2015.jpg",
                "chineseName": "克利什那·普拉萨德·加拉加",
                "englishName": "Krishna Prasad GARAGA"
            }
        ],
        "rankTrend": 11,
        "tournaments": 9,
        "points": 12567
    },
    {
        "rank": 5,
        "players": [
            {
                "id": "1511",
                "countryAbbreviation": "FRA",
                "countryFlagUrl": "https://www.badmintoncn.com/cbo_star/images/bwflag/france.png",
                "avatarUrl": "https://www.badmintoncn.com/cbo_star/upstar/1511.jpg",
                "chineseName": "托姆·吉凯尔",
                "englishName": "Thom Gicquel"
            }
        ],
        "rankTrend": 12,
        "tournaments": 12,
        "points": 11960
    },
    {
        "rank": 6,
        "players": [
            {
                "id": "3718",
                "countryAbbreviation": "FRA",
                "countryFlagUrl": "https://www.badmintoncn.com/cbo_star/images/bwflag/france.png",
                "avatarUrl": "https://www.badmintoncn.com/cbo_star/upstar/3718_1710291206.jpg",
                "chineseName": "里奥·罗西",
                "englishName": "Leo ROSSI"
            }
        ],
        "rankTrend": 12,
        "tournaments": 11,
        "points": 11740
    },
    {
        "rank": 7,
        "players": [
            {
                "id": "5403",
                "countryAbbreviation": "POL",
                "countryFlagUrl": "https://www.badmintoncn.com/cbo_star/images/bwflag/poland.png",
                "avatarUrl": "https://www.badmintoncn.com/cbo_star/upstar/5403_1698057653.jpg",
                "chineseName": "罗伯特·西布尔斯基",
                "englishName": "Robert CYBULSKI"
            }
        ],
        "rankTrend": 12,
        "tournaments": 10,
        "points": 11485
    },
    {
        "rank": 8,
        "players": [
            {
                "id": "1930",
                "countryAbbreviation": "IRL",
                "countryFlagUrl": "https://www.badmintoncn.com/cbo_star/images/bwflag/ireland.png",
                "avatarUrl": "https://www.badmintoncn.com/cbo_star/upstar/1930.jpg",
                "chineseName": "保罗·雷诺兹",
                "englishName": "Paul REYNOLDS"
            }
        ],
        "rankTrend": 12,
        "tournaments": 8,
        "points": 11210
    },
    {
        "rank": 8,
        "players": [
            {
                "id": "1759",
                "countryAbbreviation": "IRL",
                "countryFlagUrl": "https://www.badmintoncn.com/cbo_star/images/bwflag/ireland.png",
                "avatarUrl": "https://www.badmintoncn.com/cbo_star/upstar/1759.jpg",
                "chineseName": "阮日",
                "englishName": "Nhat NGUYEN"
            }
        ],
        "rankTrend": 12,
        "tournaments": 8,
        "points": 11210
    },
    {
        "rank": 10,
        "players": [
            {
                "id": "1465",
                "countryAbbreviation": "CHN",
                "countryFlagUrl": "https://www.badmintoncn.com/cbo_star/images/bwflag/china.png",
                "avatarUrl": "https://www.badmintoncn.com/cbo_star/upstar/1465_1746602900.jpg",
                "chineseName": "樊秋月",
                "englishName": "Fan Qiu Yue"
            }
        ],
        "rankTrend": 13,
        "tournaments": 5,
        "points": 10872
    },
    {
        "rank": 11,
        "players": [
            {
                "id": "1711",
                "countryAbbreviation": "KOR",
                "countryFlagUrl": "https://www.badmintoncn.com/cbo_star/images/bwflag/korea.png",
                "avatarUrl": "https://www.badmintoncn.com/cbo_star/upstar/1711.jpg",
                "chineseName": "姜珉赫",
                "englishName": "KANG Min Hyuk"
            }
        ],
        "rankTrend": 14,
        "tournaments": 9,
        "points": 10700
    },
    {
        "rank": 12,
        "players": [
            {
                "id": "1875",
                "countryAbbreviation": "SCO",
                "countryFlagUrl": "https://www.badmintoncn.com/cbo_star/images/bwflag/scotland.png",
                "avatarUrl": "https://www.badmintoncn.com/cbo_star/upstar/1875.jpg",
                "chineseName": "克里斯托弗·格里姆利",
                "englishName": "Christopher GRIMLEY"
            }
        ],
        "rankTrend": 14,
        "tournaments": 11,
        "points": 10520
    },
    {
        "rank": 12,
        "players": [
            {
                "id": "1876",
                "countryAbbreviation": "SCO",
                "countryFlagUrl": "https://www.badmintoncn.com/cbo_star/images/bwflag/scotland.png",
                "avatarUrl": "https://www.badmintoncn.com/cbo_star/upstar/1876.jpg",
                "chineseName": "马修·格里姆利",
                "englishName": "Matthew GRIMLEY"
            }
        ],
        "rankTrend": 14,
        "tournaments": 11,
        "points": 10520
    },
    {
        "rank": 14,
        "players": [
            {
                "id": "2044",
                "countryAbbreviation": "FRA",
                "countryFlagUrl": "https://www.badmintoncn.com/cbo_star/images/bwflag/france.png",
                "avatarUrl": "https://www.badmintoncn.com/cbo_star/upstar/2044.jpg",
                "chineseName": "萨米·科尔维",
                "englishName": "Samy CORVEE"
            }
        ],
        "rankTrend": 14,
        "tournaments": 11,
        "points": 10070
    },
    {
        "rank": 15,
        "players": [
            {
                "id": "1888",
                "countryAbbreviation": "FRA",
                "countryFlagUrl": "https://www.badmintoncn.com/cbo_star/images/bwflag/france.png",
                "avatarUrl": "https://www.badmintoncn.com/cbo_star/upstar/1888.jpg",
                "chineseName": "伊劳埃·亚当",
                "englishName": "Eloi ADAM"
            }
        ],
        "rankTrend": 14,
        "tournaments": 10,
        "points": 10070
    },
    {
        "rank": 16,
        "players": [
            {
                "id": "1877",
                "countryAbbreviation": "IND",
                "countryFlagUrl": "https://www.badmintoncn.com/cbo_star/images/bwflag/india.png",
                "avatarUrl": "https://www.badmintoncn.com/cbo_star/upstar/1877_1714371952.jpg",
                "chineseName": "德鲁夫·卡皮拉",
                "englishName": "DHRUV KAPILA"
            }
        ],
        "rankTrend": 14,
        "tournaments": 6,
        "points": 10027
    },
    {
        "rank": 17,
        "players": [
            {
                "id": "6265",
                "countryAbbreviation": "SWE",
                "countryFlagUrl": "https://www.badmintoncn.com/cbo_star/images/bwflag/sweden.png",
                "avatarUrl": "https://www.badmintoncn.com/cbo_star/upstar/6265_1719474760.jpg",
                "chineseName": "亚当·戈齐",
                "englishName": "Adam GOZZI"
            }
        ],
        "rankTrend": 19,
        "tournaments": 8,
        "points": 9420
    },
    {
        "rank": 17,
        "players": [
            {
                "id": "6617",
                "countryAbbreviation": "SWE",
                "countryFlagUrl": "https://www.badmintoncn.com/cbo_star/images/bwflag/sweden.png",
                "avatarUrl": "https://www.badmintoncn.com/cbo_star/upstar/6617_1719474576.jpg",
                "chineseName": "卡尔·哈巴卡",
                "englishName": "Carl HARRBACKA"
            }
        ],
        "rankTrend": 19,
        "tournaments": 8,
        "points": 9420
    },
    {
        "rank": 19,
        "players": [
            {
                "id": "2826",
                "countryAbbreviation": "TPE",
                "countryFlagUrl": "https://www.badmintoncn.com/cbo_star/images/bwflag/chinesetaipei.png",
                "avatarUrl": "https://www.badmintoncn.com/cbo_star/upstar/2826.jpg",
                "chineseName": "卢震",
                "englishName": "Lu Chen"
            }
        ],
        "rankTrend": 19,
        "tournaments": 9,
        "points": 9307
    },
    {
        "rank": 20,
        "players": [
            {
                "id": "1554",
                "countryAbbreviation": "THA",
                "countryFlagUrl": "https://www.badmintoncn.com/cbo_star/images/bwflag/thailand.png",
                "avatarUrl": "https://www.badmintoncn.com/cbo_star/upstar/1554.jpg",
                "chineseName": "瓦力",
                "englishName": "Warit Sarapat"
            }
        ],
        "rankTrend": 20,
        "tournaments": 9,
        "points": 9305
    },
    {
        "rank": 21,
        "players": [
            {
                "id": "6221",
                "countryAbbreviation": "INA",
                "countryFlagUrl": "https://www.badmintoncn.com/cbo_star/images/bwflag/indonesia.png",
                "avatarUrl": "https://www.badmintoncn.com/cbo_star/images/male.jpg",
                "chineseName": "里兹基·亚当",
                "englishName": "Rizki ADAM"
            }
        ],
        "rankTrend": 22,
        "tournaments": 6,
        "points": 9250
    },
    {
        "rank": 22,
        "players": [
            {
                "id": "1536",
                "countryAbbreviation": "MAS",
                "countryFlagUrl": "https://www.badmintoncn.com/cbo_star/images/bwflag/malaysia.png",
                "avatarUrl": "https://www.badmintoncn.com/cbo_star/upstar/1536.jpg",
                "chineseName": "万炜聪",
                "englishName": "Man Wei Chong"
            }
        ],
        "rankTrend": 22,
        "tournaments": 6,
        "points": 9227
    },
    {
        "rank": 23,
        "players": [
            {
                "id": "2230",
                "countryAbbreviation": "ITA",
                "countryFlagUrl": "https://www.badmintoncn.com/cbo_star/images/bwflag/italy.png",
                "avatarUrl": "https://www.badmintoncn.com/cbo_star/upstar/2230.jpg",
                "chineseName": "法比奥·卡波尼奥",
                "englishName": "Fabio CAPONIO"
            }
        ],
        "rankTrend": 22,
        "tournaments": 10,
        "points": 9190
    },
    {
        "rank": 24,
        "players": [
            {
                "id": "1706",
                "countryAbbreviation": "KOR",
                "countryFlagUrl": "https://www.badmintoncn.com/cbo_star/images/bwflag/korea.png",
                "avatarUrl": "https://www.badmintoncn.com/cbo_star/upstar/1706.jpg",
                "chineseName": "罗圣胜",
                "englishName": "Na Sung Seung"
            }
        ],
        "rankTrend": 23,
        "tournaments": 5,
        "points": 9115
    },
    {
        "rank": 25,
        "players": [
            {
                "id": "7233",
                "countryAbbreviation": "CZE",
                "countryFlagUrl": "https://www.badmintoncn.com/cbo_star/images/bwflag/czechrepublic.png",
                "avatarUrl": "https://www.badmintoncn.com/cbo_star/upstar/7233_1713173428.jpg",
                "chineseName": "彼得·贝兰",
                "englishName": "Petr BERAN"
            }
        ],
        "rankTrend": 23,
        "tournaments": 10,
        "points": 9060
    },
    {
        "rank": 26,
        "players": [
            {
                "id": "2210",
                "countryAbbreviation": "CZE",
                "countryFlagUrl": "https://www.badmintoncn.com/cbo_star/images/bwflag/czechrepublic.png",
                "avatarUrl": "https://www.badmintoncn.com/cbo_star/upstar/2210.jpg",
                "chineseName": "昂迪耶·克雷尔",
                "englishName": "Ondřej KRáL"
            }
        ],
        "rankTrend": 24,
        "tournaments": 10,
        "points": 8725
    },
    {
        "rank": 27,
        "players": [
            {
                "id": "6248",
                "countryAbbreviation": "CZE",
                "countryFlagUrl": "https://www.badmintoncn.com/cbo_star/images/bwflag/czechrepublic.png",
                "avatarUrl": "https://www.badmintoncn.com/cbo_star/upstar/6248_1713173716.jpg",
                "chineseName": "马修·胡巴切克",
                "englishName": "Matěj HUBáČEK"
            }
        ],
        "rankTrend": 26,
        "tournaments": 9,
        "points": 8285
    },
    {
        "rank": 28,
        "players": [
            {
                "id": "2225",
                "countryAbbreviation": "CZE",
                "countryFlagUrl": "https://www.badmintoncn.com/cbo_star/images/bwflag/czechrepublic.png",
                "avatarUrl": "https://www.badmintoncn.com/cbo_star/upstar/2225.jpg",
                "chineseName": "简·劳达",
                "englishName": "Jan LOUDA"
            }
        ],
        "rankTrend": 27,
        "tournaments": 8,
        "points": 7800
    },
    {
        "rank": 29,
        "players": [
            {
                "id": "2114",
                "countryAbbreviation": "FRA",
                "countryFlagUrl": "https://www.badmintoncn.com/cbo_star/images/bwflag/france.png",
                "avatarUrl": "https://www.badmintoncn.com/cbo_star/upstar/2114.jpg",
                "chineseName": "阿诺·梅克尔",
                "englishName": "Arnaud MERKLE"
            }
        ],
        "rankTrend": 29,
        "tournaments": 7,
        "points": 7335
    },
    {
        "rank": 30,
        "players": [
            {
                "id": "2452",
                "countryAbbreviation": "FIN",
                "countryFlagUrl": "https://www.badmintoncn.com/cbo_star/images/bwflag/finland.png",
                "avatarUrl": "https://www.badmintoncn.com/cbo_star/upstar/2452_1714292733.jpg",
                "chineseName": "安东·蒙伯格",
                "englishName": "Anton MONNBERG"
            }
        ],
        "rankTrend": 30,
        "tournaments": 6,
        "points": 7250
    },
    {
        "rank": 31,
        "players": [
            {
                "id": "2025",
                "countryAbbreviation": "FRA",
                "countryFlagUrl": "https://www.badmintoncn.com/cbo_star/images/bwflag/france.png",
                "avatarUrl": "https://www.badmintoncn.com/cbo_star/upstar/2025.jpg",
                "chineseName": "法比恩·德尔鲁",
                "englishName": "Fabien DELRUE"
            }
        ],
        "rankTrend": 30,
        "tournaments": 8,
        "points": 7190
    },
    {
        "rank": 32,
        "players": [
            {
                "id": "1555",
                "countryAbbreviation": "THA",
                "countryFlagUrl": "https://www.badmintoncn.com/cbo_star/images/bwflag/thailand.png",
                "avatarUrl": "https://www.badmintoncn.com/cbo_star/upstar/1555.jpg",
                "chineseName": "昆拉武特·威提讪",
                "englishName": "Kunlavut VITIDSARN"
            }
        ],
        "rankTrend": 30,
        "tournaments": 5,
        "points": 7180
    },
    {
        "rank": 32,
        "players": [
            {
                "id": "5513",
                "countryAbbreviation": "THA",
                "countryFlagUrl": "https://www.badmintoncn.com/cbo_star/images/bwflag/thailand.png",
                "avatarUrl": "https://www.badmintoncn.com/cbo_star/upstar/5513_1730085868.jpg",
                "chineseName": "塞塔南·皮亚沃瓦拉维吉特",
                "englishName": "Setthanan PIYAWATCHARAVIJIT"
            }
        ],
        "rankTrend": 30,
        "tournaments": 5,
        "points": 7180
    },
    {
        "rank": 34,
        "players": [
            {
                "id": "1475",
                "countryAbbreviation": "KOR",
                "countryFlagUrl": "https://www.badmintoncn.com/cbo_star/images/bwflag/korea.png",
                "avatarUrl": "https://www.badmintoncn.com/cbo_star/upstar/1475.jpg",
                "chineseName": "金元浩",
                "englishName": "Kim Won Ho"
            }
        ],
        "rankTrend": 30,
        "tournaments": 7,
        "points": 7177
    },
    {
        "rank": 35,
        "players": [
            {
                "id": "5868",
                "countryAbbreviation": "POL",
                "countryFlagUrl": "https://www.badmintoncn.com/cbo_star/images/bwflag/poland.png",
                "avatarUrl": "https://www.badmintoncn.com/cbo_star/upstar/5868_1698828019.jpg",
                "chineseName": "亚当·索尔克",
                "englishName": "Adam SZOLC"
            }
        ],
        "rankTrend": 30,
        "tournaments": 10,
        "points": 7105
    },
    {
        "rank": 36,
        "players": [
            {
                "id": "5657",
                "countryAbbreviation": "RUS",
                "countryFlagUrl": "https://www.badmintoncn.com/cbo_star/images/bwflag/russia.png",
                "avatarUrl": "https://www.badmintoncn.com/cbo_star/upstar/5657_1738812259.jpg",
                "chineseName": "德米特里·克里缅科",
                "englishName": "Dmitrii KLIMENKO"
            }
        ],
        "rankTrend": 33,
        "tournaments": 5,
        "points": 6930
    },
    {
        "rank": 37,
        "players": [
            {
                "id": "1915",
                "countryAbbreviation": "ENG",
                "countryFlagUrl": "https://www.badmintoncn.com/cbo_star/images/bwflag/england.png",
                "avatarUrl": "https://www.badmintoncn.com/cbo_star/upstar/1915.jpg",
                "chineseName": "史蒂文·斯托伍德",
                "englishName": "Steven STALLWOOD"
            }
        ],
        "rankTrend": 34,
        "tournaments": 7,
        "points": 6720
    },
    {
        "rank": 38,
        "players": [
            {
                "id": "3975",
                "countryAbbreviation": "SUI",
                "countryFlagUrl": "https://www.badmintoncn.com/cbo_star/images/bwflag/switzerland.png",
                "avatarUrl": "https://www.badmintoncn.com/cbo_star/upstar/3975.jpg",
                "chineseName": "朱利安·谢维勒",
                "englishName": "Julien SCHEIWILLER"
            }
        ],
        "rankTrend": 35,
        "tournaments": 8,
        "points": 6700
    },
    {
        "rank": 39,
        "players": [
            {
                "id": "3756",
                "countryAbbreviation": "SRB",
                "countryFlagUrl": "https://www.badmintoncn.com/cbo_star/images/bwflag/serbia.png",
                "avatarUrl": "https://www.badmintoncn.com/cbo_star/upstar/3756.jpg",
                "chineseName": "卢卡·米利奇",
                "englishName": "Luka MILIC"
            }
        ],
        "rankTrend": 36,
        "tournaments": 7,
        "points": 6465
    },
    {
        "rank": 40,
        "players": [
            {
                "id": "7240",
                "countryAbbreviation": "FIN",
                "countryFlagUrl": "https://www.badmintoncn.com/cbo_star/images/bwflag/finland.png",
                "avatarUrl": "https://www.badmintoncn.com/cbo_star/upstar/7240_1716446966.jpg",
                "chineseName": "贾斯图斯·基尔皮",
                "englishName": "Justus KILPI"
            }
        ],
        "rankTrend": 36,
        "tournaments": 6,
        "points": 6160
    },
    {
        "rank": 41,
        "players": [
            {
                "id": "1535",
                "countryAbbreviation": "MAS",
                "countryFlagUrl": "https://www.badmintoncn.com/cbo_star/images/bwflag/malaysia.png",
                "avatarUrl": "https://www.badmintoncn.com/cbo_star/upstar/1535_1708332588.jpg",
                "chineseName": "梁峻豪",
                "englishName": "Leong Jun Hao"
            }
        ],
        "rankTrend": 36,
        "tournaments": 3,
        "points": 6150
    },
    {
        "rank": 42,
        "players": [
            {
                "id": "6563",
                "countryAbbreviation": "KOR",
                "countryFlagUrl": "https://www.badmintoncn.com/cbo_star/images/bwflag/korea.png",
                "avatarUrl": "https://www.badmintoncn.com/cbo_star/upstar/6563_1715321517.jpg",
                "chineseName": "金门俊",
                "englishName": "Moon Jun KIM"
            }
        ],
        "rankTrend": 39,
        "tournaments": 4,
        "points": 5805
    },
    {
        "rank": 43,
        "players": [
            {
                "id": "2579",
                "countryAbbreviation": "HKG",
                "countryFlagUrl": "https://www.badmintoncn.com/cbo_star/images/bwflag/hongkongchina.png",
                "avatarUrl": "https://www.badmintoncn.com/cbo_star/upstar/2579.jpg",
                "chineseName": "邹轩朗",
                "englishName": "CHOW Hin Long"
            }
        ],
        "rankTrend": 40,
        "tournaments": 6,
        "points": 5597
    },
    {
        "rank": 44,
        "players": [
            {
                "id": "2119",
                "countryAbbreviation": "ENG",
                "countryFlagUrl": "https://www.badmintoncn.com/cbo_star/images/bwflag/england.png",
                "avatarUrl": "https://www.badmintoncn.com/cbo_star/upstar/2119.jpg",
                "chineseName": "卡勒姆·亨明",
                "englishName": "Callum HEMMING"
            }
        ],
        "rankTrend": 40,
        "tournaments": 11,
        "points": 5560
    },
    {
        "rank": 45,
        "players": [
            {
                "id": "1705",
                "countryAbbreviation": "KOR",
                "countryFlagUrl": "https://www.badmintoncn.com/cbo_star/images/bwflag/korea.png",
                "avatarUrl": "https://www.badmintoncn.com/cbo_star/upstar/1705.jpg",
                "chineseName": "李相旼",
                "englishName": "Sang Min Lee"
            }
        ],
        "rankTrend": 41,
        "tournaments": 5,
        "points": 5535
    },
    {
        "rank": 46,
        "players": [
            {
                "id": "19370",
                "countryAbbreviation": "SRB",
                "countryFlagUrl": "https://www.badmintoncn.com/cbo_star/images/bwflag/serbia.png",
                "avatarUrl": "https://www.badmintoncn.com/cbo_star/images/male.jpg",
                "chineseName": "内纳德·米洛舍维奇",
                "englishName": "Nenad MILOSEVIC"
            }
        ],
        "rankTrend": 41,
        "tournaments": 7,
        "points": 5525
    },
    {
        "rank": 47,
        "players": [
            {
                "id": "2519",
                "countryAbbreviation": "HUN",
                "countryFlagUrl": "https://www.badmintoncn.com/cbo_star/images/bwflag/hungary.png",
                "avatarUrl": "https://www.badmintoncn.com/cbo_star/upstar/2519.jpg",
                "chineseName": "格戈·皮特尔",
                "englishName": "Gergo Pytel"
            }
        ],
        "rankTrend": 41,
        "tournaments": 13,
        "points": 5520
    },
    {
        "rank": 47,
        "players": [
            {
                "id": "7269",
                "countryAbbreviation": "HUN",
                "countryFlagUrl": "https://www.badmintoncn.com/cbo_star/images/bwflag/hungary.png",
                "avatarUrl": "https://www.badmintoncn.com/cbo_star/upstar/7269_1715064713.jpg",
                "chineseName": "巴拉兹·森贾伊",
                "englishName": "Balazs SZENJAI"
            }
        ],
        "rankTrend": 41,
        "tournaments": 13,
        "points": 5520
    },
    {
        "rank": 49,
        "players": [
            {
                "id": "7436",
                "countryAbbreviation": "KOR",
                "countryFlagUrl": "https://www.badmintoncn.com/cbo_star/images/bwflag/korea.png",
                "avatarUrl": "https://www.badmintoncn.com/cbo_star/upstar/7436_1732524386.jpg",
                "chineseName": "李学范",
                "englishName": "Hak Beom LEE"
            }
        ],
        "rankTrend": 42,
        "tournaments": 5,
        "points": 5430
    },
    {
        "rank": 50,
        "players": [
            {
                "id": "3633",
                "countryAbbreviation": "ZAM",
                "countryFlagUrl": "https://www.badmintoncn.com/cbo_star/images/bwflag/zambia.png",
                "avatarUrl": "https://www.badmintoncn.com/cbo_star/upstar/3633_1702631498.jpg",
                "chineseName": "卡隆博·穆伦加",
                "englishName": "Kalombo MULENGA"
            }
        ],
        "rankTrend": 44,
        "tournaments": 4,
        "points": 5250
    },
    {
        "rank": 51,
        "players": [
            {
                "id": "6577",
                "countryAbbreviation": "RUS",
                "countryFlagUrl": "https://www.badmintoncn.com/cbo_star/images/bwflag/russia.png",
                "avatarUrl": "https://www.badmintoncn.com/cbo_star/upstar/6577.jpg",
                "chineseName": "米哈伊尔·拉夫里科夫",
                "englishName": "Mikhail LAVRIKOV"
            }
        ],
        "rankTrend": 46,
        "tournaments": 4,
        "points": 5120
    },
    {
        "rank": 52,
        "players": [
            {
                "id": "4686",
                "countryAbbreviation": "MAC",
                "countryFlagUrl": "https://www.badmintoncn.com/cbo_star/images/bwflag/macao.png",
                "avatarUrl": "https://www.badmintoncn.com/cbo_star/upstar/4686.jpg",
                "chineseName": "裴鹏锋",
                "englishName": "Pang Fong PUI"
            }
        ],
        "rankTrend": 49,
        "tournaments": 7,
        "points": 5010
    },
    {
        "rank": 53,
        "players": [
            {
                "id": "2500",
                "countryAbbreviation": "ENG",
                "countryFlagUrl": "https://www.badmintoncn.com/cbo_star/images/bwflag/england.png",
                "avatarUrl": "https://www.badmintoncn.com/cbo_star/upstar/2500.jpg",
                "chineseName": "约翰尼·托朱森",
                "englishName": "Johnnie TORJUSSEN"
            }
        ],
        "rankTrend": 49,
        "tournaments": 10,
        "points": 4990
    },
    {
        "rank": 54,
        "players": [
            {
                "id": "5436",
                "countryAbbreviation": "SRB",
                "countryFlagUrl": "https://www.badmintoncn.com/cbo_star/images/bwflag/serbia.png",
                "avatarUrl": "https://www.badmintoncn.com/cbo_star/upstar/5436_1711337063.jpg",
                "chineseName": "马特亚·曼尼奇",
                "englishName": "Mateja MANIC"
            }
        ],
        "rankTrend": 50,
        "tournaments": 8,
        "points": 4960
    },
    {
        "rank": 55,
        "players": [
            {
                "id": "10955",
                "countryAbbreviation": "CHI",
                "countryFlagUrl": "https://www.badmintoncn.com/cbo_star/images/bwflag/chile.png",
                "avatarUrl": "https://www.badmintoncn.com/cbo_star/upstar/10955_1703472868.jpg",
                "chineseName": "克里斯蒂安·阿拉亚",
                "englishName": "Cristian ARAYA"
            }
        ],
        "rankTrend": 53,
        "tournaments": 3,
        "points": 4870
    },
    {
        "rank": 56,
        "players": [
            {
                "id": "6589",
                "countryAbbreviation": "SUI",
                "countryFlagUrl": "https://www.badmintoncn.com/cbo_star/images/bwflag/switzerland.png",
                "avatarUrl": "https://www.badmintoncn.com/cbo_star/upstar/6589_1718595691.jpg",
                "chineseName": "大卫·奥尔特乌",
                "englishName": "David ORTEU"
            }
        ],
        "rankTrend": 53,
        "tournaments": 6,
        "points": 4860
    },
    {
        "rank": 57,
        "players": [
            {
                "id": "6612",
                "countryAbbreviation": "MAS",
                "countryFlagUrl": "https://www.badmintoncn.com/cbo_star/images/bwflag/malaysia.png",
                "avatarUrl": "https://www.badmintoncn.com/cbo_star/upstar/6612_1721810618.jpg",
                "chineseName": "柯毅健",
                "englishName": "KWEK Yee Jian"
            }
        ],
        "rankTrend": 54,
        "tournaments": 3,
        "points": 4810
    },
    {
        "rank": 58,
        "players": [
            {
                "id": "1914",
                "countryAbbreviation": "ENG",
                "countryFlagUrl": "https://www.badmintoncn.com/cbo_star/images/bwflag/england.png",
                "avatarUrl": "https://www.badmintoncn.com/cbo_star/upstar/1914.jpg",
                "chineseName": "扎克·鲁斯",
                "englishName": "Zach RUSS"
            }
        ],
        "rankTrend": 54,
        "tournaments": 5,
        "points": 4700
    },
    {
        "rank": 59,
        "players": [
            {
                "id": "2348",
                "countryAbbreviation": "BEL",
                "countryFlagUrl": "https://www.badmintoncn.com/cbo_star/images/bwflag/belgium.png",
                "avatarUrl": "https://www.badmintoncn.com/cbo_star/upstar/2348.jpg",
                "chineseName": "朱利安·卡拉吉",
                "englishName": "Julien CARRAGGI"
            }
        ],
        "rankTrend": 54,
        "tournaments": 7,
        "points": 4692
    },
    {
        "rank": 60,
        "players": [
            {
                "id": "6580",
                "countryAbbreviation": "SVK",
                "countryFlagUrl": "https://www.badmintoncn.com/cbo_star/images/bwflag/slovakia.png",
                "avatarUrl": "https://www.badmintoncn.com/cbo_star/upstar/6580_1715327206.jpg",
                "chineseName": "亚当·霍拉克",
                "englishName": "Adam HORAK"
            }
        ],
        "rankTrend": 56,
        "tournaments": 8,
        "points": 4635
    },
    {
        "rank": 61,
        "players": [
            {
                "id": "5131",
                "countryAbbreviation": "ESP",
                "countryFlagUrl": "https://www.badmintoncn.com/cbo_star/images/bwflag/spain.png",
                "avatarUrl": "https://www.badmintoncn.com/cbo_star/upstar/5131_1717385417.jpg",
                "chineseName": "阿尔瓦罗·巴斯克斯",
                "englishName": "Alvaro VAZQUEZ"
            }
        ],
        "rankTrend": 56,
        "tournaments": 7,
        "points": 4600
    },
    {
        "rank": 62,
        "players": [
            {
                "id": "2829",
                "countryAbbreviation": "TPE",
                "countryFlagUrl": "https://www.badmintoncn.com/cbo_star/images/bwflag/chinesetaipei.png",
                "avatarUrl": "https://www.badmintoncn.com/cbo_star/upstar/2829.jpg",
                "chineseName": "苏力玮",
                "englishName": "SU Li Wei"
            }
        ],
        "rankTrend": 56,
        "tournaments": 4,
        "points": 4600
    },
    {
        "rank": 62,
        "players": [
            {
                "id": "1926",
                "countryAbbreviation": "TPE",
                "countryFlagUrl": "https://www.badmintoncn.com/cbo_star/images/bwflag/chinesetaipei.png",
                "avatarUrl": "https://www.badmintoncn.com/cbo_star/upstar/1926.jpg",
                "chineseName": "叶宏蔚",
                "englishName": "YE Hong Wei"
            }
        ],
        "rankTrend": 56,
        "tournaments": 4,
        "points": 4600
    },
    {
        "rank": 64,
        "players": [
            {
                "id": "5201",
                "countryAbbreviation": "TUR",
                "countryFlagUrl": "https://www.badmintoncn.com/cbo_star/images/bwflag/turkey.png",
                "avatarUrl": "https://www.badmintoncn.com/cbo_star/upstar/5201_1715825940.jpg",
                "chineseName": "埃姆雷·桑梅斯",
                "englishName": "Emre SONMEZ"
            }
        ],
        "rankTrend": 56,
        "tournaments": 5,
        "points": 4530
    },
    {
        "rank": 64,
        "players": [
            {
                "id": "5200",
                "countryAbbreviation": "TUR",
                "countryFlagUrl": "https://www.badmintoncn.com/cbo_star/images/bwflag/turkey.png",
                "avatarUrl": "https://www.badmintoncn.com/cbo_star/upstar/5200_1743063233.jpg",
                "chineseName": "穆罕默德·卡帕尔",
                "englishName": "Mehmet CAPAR"
            }
        ],
        "rankTrend": 56,
        "tournaments": 5,
        "points": 4530
    },
    {
        "rank": 66,
        "players": [
            {
                "id": "6073",
                "countryAbbreviation": "KAZ",
                "countryFlagUrl": "https://www.badmintoncn.com/cbo_star/images/bwflag/kazakhstan.png",
                "avatarUrl": "https://www.badmintoncn.com/cbo_star/upstar/6073_1744272235.jpg",
                "chineseName": "伊克拉姆詹·尤尔达舍夫",
                "englishName": "Ikramzhan YULDASHEV"
            }
        ],
        "rankTrend": 59,
        "tournaments": 3,
        "points": 4500
    },
    {
        "rank": 66,
        "players": [
            {
                "id": "2587",
                "countryAbbreviation": "KAZ",
                "countryFlagUrl": "https://www.badmintoncn.com/cbo_star/images/bwflag/kazakhstan.png",
                "avatarUrl": "https://www.badmintoncn.com/cbo_star/upstar/2587.jpg",
                "chineseName": "德米特里·帕纳林",
                "englishName": "Dmitriy PANARIN"
            }
        ],
        "rankTrend": 59,
        "tournaments": 3,
        "points": 4500
    },
    {
        "rank": 68,
        "players": [
            {
                "id": "2451",
                "countryAbbreviation": "FIN",
                "countryFlagUrl": "https://www.badmintoncn.com/cbo_star/images/bwflag/finland.png",
                "avatarUrl": "https://www.badmintoncn.com/cbo_star/upstar/2451_1739243191.jpg",
                "chineseName": "杰斯珀·保罗",
                "englishName": "Jesper PAUL"
            }
        ],
        "rankTrend": 63,
        "tournaments": 7,
        "points": 4362
    },
    {
        "rank": 69,
        "players": [
            {
                "id": "5829",
                "countryAbbreviation": "IND",
                "countryFlagUrl": "https://www.badmintoncn.com/cbo_star/images/bwflag/india.png",
                "avatarUrl": "https://www.badmintoncn.com/cbo_star/upstar/5829_1731295057.jpg",
                "chineseName": "布里杰什·亚达夫",
                "englishName": "Brijesh YADAV"
            }
        ],
        "rankTrend": 63,
        "tournaments": 4,
        "points": 4355
    },
    {
        "rank": 70,
        "players": [
            {
                "id": "2184",
                "countryAbbreviation": "DEN",
                "countryFlagUrl": "https://www.badmintoncn.com/cbo_star/images/bwflag/denmark.png",
                "avatarUrl": "https://www.badmintoncn.com/cbo_star/upstar/2184_1749180340.jpg",
                "chineseName": "杰斯帕·托夫特",
                "englishName": "Jesper TOFT"
            }
        ],
        "rankTrend": 63,
        "tournaments": 4,
        "points": 4337
    },
    {
        "rank": 71,
        "players": [
            {
                "id": "10492",
                "countryAbbreviation": "PYF",
                "countryFlagUrl": "https://www.badmintoncn.com/cbo_star/images/bwflag/french-polynesia.png",
                "avatarUrl": "https://www.badmintoncn.com/cbo_star/images/male.jpg",
                "chineseName": "Quentin BERNAIX",
                "englishName": "Quentin BERNAIX"
            }
        ],
        "rankTrend": 67,
        "tournaments": 3,
        "points": 4215
    },
    {
        "rank": 71,
        "players": [
            {
                "id": "12399",
                "countryAbbreviation": "PYF",
                "countryFlagUrl": "https://www.badmintoncn.com/cbo_star/images/bwflag/french-polynesia.png",
                "avatarUrl": "https://www.badmintoncn.com/cbo_star/images/male.jpg",
                "chineseName": "Hugo SAUTEREAU",
                "englishName": "Hugo SAUTEREAU"
            }
        ],
        "rankTrend": 67,
        "tournaments": 3,
        "points": 4215
    },
    {
        "rank": 73,
        "players": [
            {
                "id": "2502",
                "countryAbbreviation": "ITA",
                "countryFlagUrl": "https://www.badmintoncn.com/cbo_star/images/bwflag/italy.png",
                "avatarUrl": "https://www.badmintoncn.com/cbo_star/upstar/2502_1722416238.jpg",
                "chineseName": "乔瓦尼·托蒂",
                "englishName": "Giovanni TOTI"
            }
        ],
        "rankTrend": 67,
        "tournaments": 6,
        "points": 4200
    },
    {
        "rank": 74,
        "players": [
            {
                "id": "8190",
                "countryAbbreviation": "AUT",
                "countryFlagUrl": "https://www.badmintoncn.com/cbo_star/images/bwflag/austria.png",
                "avatarUrl": "https://www.badmintoncn.com/cbo_star/upstar/8190_1710732294.jpg",
                "chineseName": "雅各布·索尔格",
                "englishName": "Jakob SORGER"
            }
        ],
        "rankTrend": 70,
        "tournaments": 5,
        "points": 4070
    },
    {
        "rank": 75,
        "players": [
            {
                "id": "7253",
                "countryAbbreviation": "MEX",
                "countryFlagUrl": "https://www.badmintoncn.com/cbo_star/images/bwflag/mexico.png",
                "avatarUrl": "https://www.badmintoncn.com/cbo_star/upstar/7253_1722245645.jpg",
                "chineseName": "阿图罗·巴拉哈斯·洛佩斯",
                "englishName": "Jesus Arturo BARAJAS LOPEZ"
            }
        ],
        "rankTrend": 71,
        "tournaments": 3,
        "points": 4002
    },
    {
        "rank": 75,
        "players": [
            {
                "id": "2138",
                "countryAbbreviation": "MEX",
                "countryFlagUrl": "https://www.badmintoncn.com/cbo_star/images/bwflag/mexico.png",
                "avatarUrl": "https://www.badmintoncn.com/cbo_star/upstar/2138.jpg",
                "chineseName": "路易斯·阿曼多·蒙托亚·纳瓦罗",
                "englishName": "Luis Armando MONTOYA NAVARRO"
            }
        ],
        "rankTrend": 71,
        "tournaments": 3,
        "points": 4002
    },
    {
        "rank": 77,
        "players": [
            {
                "id": "6326",
                "countryAbbreviation": "PER",
                "countryFlagUrl": "https://www.badmintoncn.com/cbo_star/images/bwflag/peru.png",
                "avatarUrl": "https://www.badmintoncn.com/cbo_star/upstar/6326_1711592420.jpg",
                "chineseName": "尼古拉斯·马西亚斯",
                "englishName": "Nicolas MACIAS"
            }
        ],
        "rankTrend": 71,
        "tournaments": 3,
        "points": 3980
    },
    {
        "rank": 78,
        "players": [
            {
                "id": "7298",
                "countryAbbreviation": "FIN",
                "countryFlagUrl": "https://www.badmintoncn.com/cbo_star/images/bwflag/finland.png",
                "avatarUrl": "https://www.badmintoncn.com/cbo_star/upstar/7298_1715934947.jpg",
                "chineseName": "乔那·普罗",
                "englishName": "Joona PURO"
            }
        ],
        "rankTrend": 71,
        "tournaments": 6,
        "points": 3940
    },
    {
        "rank": 79,
        "players": [
            {
                "id": "10618",
                "countryAbbreviation": "POL",
                "countryFlagUrl": "https://www.badmintoncn.com/cbo_star/images/bwflag/poland.png",
                "avatarUrl": "https://www.badmintoncn.com/cbo_star/upstar/10618_1716798226.jpg",
                "chineseName": "沃伊切赫·萨伊多克",
                "englishName": "Wojciech SAJDOK"
            }
        ],
        "rankTrend": 74,
        "tournaments": 6,
        "points": 3840
    },
    {
        "rank": 80,
        "players": [
            {
                "id": "2248",
                "countryAbbreviation": "SGP",
                "countryFlagUrl": "https://www.badmintoncn.com/cbo_star/images/bwflag/singapore.png",
                "avatarUrl": "https://www.badmintoncn.com/cbo_star/upstar/2248.jpg",
                "chineseName": "郭俊良",
                "englishName": "Jun Liang Andy KWEK"
            }
        ],
        "rankTrend": 76,
        "tournaments": 5,
        "points": 3802
    },
    {
        "rank": 81,
        "players": [
            {
                "id": "19701",
                "countryAbbreviation": "INA",
                "countryFlagUrl": "https://www.badmintoncn.com/cbo_star/images/bwflag/indonesia.png",
                "avatarUrl": "https://www.badmintoncn.com/cbo_star/upstar/19701_1749438097.jpg",
                "chineseName": "菲萨尔·维拉托",
                "englishName": "Fiesal WIRANTO"
            }
        ],
        "rankTrend": 79,
        "tournaments": 3,
        "points": 3605
    },
    {
        "rank": 82,
        "players": [
            {
                "id": "6358",
                "countryAbbreviation": "PER",
                "countryFlagUrl": "https://www.badmintoncn.com/cbo_star/images/bwflag/peru.png",
                "avatarUrl": "https://www.badmintoncn.com/cbo_star/upstar/6358_1711507460.jpg",
                "chineseName": "布鲁诺·巴鲁埃托·德扎",
                "englishName": "Bruno BARRUETO DEZA"
            }
        ],
        "rankTrend": 79,
        "tournaments": 5,
        "points": 3592
    },
    {
        "rank": 83,
        "players": [
            {
                "id": "3818",
                "countryAbbreviation": "PER",
                "countryFlagUrl": "https://www.badmintoncn.com/cbo_star/images/bwflag/peru.png",
                "avatarUrl": "https://www.badmintoncn.com/cbo_star/upstar/3818_1711335492.jpg",
                "chineseName": "迭戈·苏巴斯特·德村",
                "englishName": "Diego SUBAUSTE TOKUMURA"
            }
        ],
        "rankTrend": 79,
        "tournaments": 5,
        "points": 3590
    },
    {
        "rank": 84,
        "players": [
            {
                "id": "6622",
                "countryAbbreviation": "POL",
                "countryFlagUrl": "https://www.badmintoncn.com/cbo_star/images/bwflag/poland.png",
                "avatarUrl": "https://www.badmintoncn.com/cbo_star/upstar/6622_1713844248.jpg",
                "chineseName": "康拉德·普洛赫",
                "englishName": "Konrad PLOCH"
            }
        ],
        "rankTrend": 79,
        "tournaments": 4,
        "points": 3580
    },
    {
        "rank": 85,
        "players": [
            {
                "id": "12050",
                "countryAbbreviation": "PER",
                "countryFlagUrl": "https://www.badmintoncn.com/cbo_star/images/bwflag/peru.png",
                "avatarUrl": "https://www.badmintoncn.com/cbo_star/images/male.jpg",
                "chineseName": "古斯塔沃·阿尔弗雷多·萨拉扎尔",
                "englishName": "Gustavo Alfredo SALAZAR"
            }
        ],
        "rankTrend": 79,
        "tournaments": 3,
        "points": 3570
    },
    {
        "rank": 86,
        "players": [
            {
                "id": "7266",
                "countryAbbreviation": "ESP",
                "countryFlagUrl": "https://www.badmintoncn.com/cbo_star/images/bwflag/spain.png",
                "avatarUrl": "https://www.badmintoncn.com/cbo_star/upstar/7266_1717398581.jpg",
                "chineseName": "米格尔·巴尔巴多",
                "englishName": "MIGUEL BARBADO"
            }
        ],
        "rankTrend": 80,
        "tournaments": 5,
        "points": 3540
    },
    {
        "rank": 87,
        "players": [
            {
                "id": "3845",
                "countryAbbreviation": "FRA",
                "countryFlagUrl": "https://www.badmintoncn.com/cbo_star/images/bwflag/france.png",
                "avatarUrl": "https://www.badmintoncn.com/cbo_star/upstar/3845_1716964737.jpg",
                "chineseName": "马克西姆·布里奥特",
                "englishName": "Maxime BRIOT"
            }
        ],
        "rankTrend": 80,
        "tournaments": 5,
        "points": 3530
    },
    {
        "rank": 88,
        "players": [
            {
                "id": "19603",
                "countryAbbreviation": "POL",
                "countryFlagUrl": "https://www.badmintoncn.com/cbo_star/images/bwflag/poland.png",
                "avatarUrl": "https://www.badmintoncn.com/cbo_star/upstar/19603_1749632015.jpg",
                "chineseName": "拉多斯瓦夫·沃贝尔",
                "englishName": "Radoslaw WROBEL"
            }
        ],
        "rankTrend": 80,
        "tournaments": 5,
        "points": 3515
    },
    {
        "rank": 89,
        "players": [
            {
                "id": "1700",
                "countryAbbreviation": "INA",
                "countryFlagUrl": "https://www.badmintoncn.com/cbo_star/images/bwflag/indonesia.png",
                "avatarUrl": "https://www.badmintoncn.com/cbo_star/upstar/1700.jpg",
                "chineseName": "雷汉·诺法勒·库沙扬托",
                "englishName": "Rehan Naufal Kusharjanto"
            }
        ],
        "rankTrend": 80,
        "tournaments": 4,
        "points": 3455
    },
    {
        "rank": 90,
        "players": [
            {
                "id": "1913",
                "countryAbbreviation": "MAS",
                "countryFlagUrl": "https://www.badmintoncn.com/cbo_star/images/bwflag/malaysia.png",
                "avatarUrl": "https://www.badmintoncn.com/cbo_star/upstar/1913.jpg",
                "chineseName": "吴永昌",
                "englishName": "NG Eng Cheong"
            }
        ],
        "rankTrend": 80,
        "tournaments": 3,
        "points": 3435
    },
    {
        "rank": 91,
        "players": [
            {
                "id": "6011",
                "countryAbbreviation": "MAC",
                "countryFlagUrl": "https://www.badmintoncn.com/cbo_star/images/bwflag/macao.png",
                "avatarUrl": "https://www.badmintoncn.com/cbo_star/upstar/6011_1700448368.jpg",
                "chineseName": "谢霈毅",
                "englishName": "Pui Ngai CHE"
            }
        ],
        "rankTrend": 81,
        "tournaments": 5,
        "points": 3400
    },
    {
        "rank": 92,
        "players": [
            {
                "id": "19699",
                "countryAbbreviation": "INA",
                "countryFlagUrl": "https://www.badmintoncn.com/cbo_star/images/bwflag/indonesia.png",
                "avatarUrl": "https://www.badmintoncn.com/cbo_star/upstar/19699_1749437900.jpg",
                "chineseName": "穆罕默德·陶菲库尔·哈菲兹",
                "englishName": "Muhammad Taufiqul HAFIZH"
            }
        ],
        "rankTrend": 81,
        "tournaments": 3,
        "points": 3395
    },
    {
        "rank": 93,
        "players": [
            {
                "id": "7250",
                "countryAbbreviation": "EST",
                "countryFlagUrl": "https://www.badmintoncn.com/cbo_star/images/bwflag/estonia.png",
                "avatarUrl": "https://www.badmintoncn.com/cbo_star/upstar/7250_1715247686.jpg",
                "chineseName": "马库斯·洛",
                "englishName": "Marcus LÕO"
            }
        ],
        "rankTrend": 82,
        "tournaments": 5,
        "points": 3312
    },
    {
        "rank": 94,
        "players": [
            {
                "id": "10673",
                "countryAbbreviation": "TUR",
                "countryFlagUrl": "https://www.badmintoncn.com/cbo_star/images/bwflag/turkey.png",
                "avatarUrl": "https://www.badmintoncn.com/cbo_star/images/male.jpg",
                "chineseName": "塞尔坎·乌古鲁",
                "englishName": "Serkan UGURLU"
            }
        ],
        "rankTrend": 84,
        "tournaments": 4,
        "points": 3260
    },
    {
        "rank": 95,
        "players": [
            {
                "id": "2527",
                "countryAbbreviation": "ESP",
                "countryFlagUrl": "https://www.badmintoncn.com/cbo_star/images/bwflag/spain.png",
                "avatarUrl": "https://www.badmintoncn.com/cbo_star/upstar/2527_1733985498.jpg",
                "chineseName": "何塞·摩尔",
                "englishName": "Jose MOLARES"
            }
        ],
        "rankTrend": 84,
        "tournaments": 4,
        "points": 3220
    },
    {
        "rank": 96,
        "players": [
            {
                "id": "6067",
                "countryAbbreviation": "MYA",
                "countryFlagUrl": "https://www.badmintoncn.com/cbo_star/images/bwflag/myanmar.png",
                "avatarUrl": "https://www.badmintoncn.com/cbo_star/upstar/6067_1712905426.jpg",
                "chineseName": "胡图昂妙",
                "englishName": "HTOO Aung Myo"
            }
        ],
        "rankTrend": 84,
        "tournaments": 3,
        "points": 3200
    },
    {
        "rank": 97,
        "players": [
            {
                "id": "12112",
                "countryAbbreviation": "PER",
                "countryFlagUrl": "https://www.badmintoncn.com/cbo_star/images/bwflag/peru.png",
                "avatarUrl": "https://www.badmintoncn.com/cbo_star/images/male.jpg",
                "chineseName": "Alfonso GARCIA-ROSELL",
                "englishName": "Alfonso GARCIA-ROSELL"
            }
        ],
        "rankTrend": 84,
        "tournaments": 3,
        "points": 3190
    },
    {
        "rank": 98,
        "players": [
            {
                "id": "1927",
                "countryAbbreviation": "MAS",
                "countryFlagUrl": "https://www.badmintoncn.com/cbo_star/images/bwflag/malaysia.png",
                "avatarUrl": "https://www.badmintoncn.com/cbo_star/upstar/1927.jpg",
                "chineseName": "郑宇骏",
                "englishName": "Yee Jun CHANG"
            }
        ],
        "rankTrend": 84,
        "tournaments": 3,
        "points": 3160
    },
    {
        "rank": 99,
        "players": [
            {
                "id": "2490",
                "countryAbbreviation": "THA",
                "countryFlagUrl": "https://www.badmintoncn.com/cbo_star/images/bwflag/thailand.png",
                "avatarUrl": "https://www.badmintoncn.com/cbo_star/upstar/2490_1705928228.jpg",
                "chineseName": "蓬萨科恩·通康",
                "englishName": "Pongsakorn THONGKHAM"
            }
        ],
        "rankTrend": 84,
        "tournaments": 7,
        "points": 3140
    },
    {
        "rank": 100,
        "players": [
            {
                "id": "5520",
                "countryAbbreviation": "AUT",
                "countryFlagUrl": "https://www.badmintoncn.com/cbo_star/images/bwflag/austria.png",
                "avatarUrl": "https://www.badmintoncn.com/cbo_star/upstar/5520_1710998990.jpg",
                "chineseName": "尼古拉斯·鲁道夫",
                "englishName": "Nicolas RUDOLF"
            }
        ],
        "rankTrend": 84,
        "tournaments": 4,
        "points": 3140
    }
]